<?xml version="1.0" encoding="UTF-8" standalone="no"?>

<!DOCTYPE paula SYSTEM "paula_feat.dtd">
<paula version="1.0">

<header paula_id="sahidica.Mark_15_orig"/>

<featList xmlns:xlink="http://www.w3.org/1999/xlink" type="orig" xml:base="sahidica.Mark_15.origSeg.xml">
<feat xlink:href="#orig_1" value="ϩⲧⲟⲟⲩⲉ"/><!-- ϩⲧⲟⲟⲩⲉ -->
<feat xlink:href="#orig_2" value="ⲇⲉ"/><!-- ⲇⲉ -->
<feat xlink:href="#orig_3" value="ⲛⲧⲉⲣⲉ"/><!-- ⲛⲧⲉⲣⲉ -->
<feat xlink:href="#orig_4" value="ϥ"/><!-- ϥ -->
<feat xlink:href="#orig_5" value="ϣⲱⲡⲉ"/><!-- ϣⲱⲡⲉ -->
<feat xlink:href="#orig_6" value="ⲁ"/><!-- ⲁ -->
<feat xlink:href="#orig_7" value="ⲩ"/><!-- ⲩ -->
<feat xlink:href="#orig_8" value="ϫⲓ"/><!-- ϫⲓ -->
<feat xlink:href="#orig_9" value="ϣⲟϫⲛⲉ"/><!-- ϣⲟϫⲛⲉ -->
<feat xlink:href="#orig_10" value="ⲛϭⲓ"/><!-- ⲛϭⲓ -->
<feat xlink:href="#orig_11" value="ⲛ"/><!-- ⲛ -->
<feat xlink:href="#orig_12" value="ⲁⲣⲭⲓⲉⲣⲉⲩⲥ"/><!-- ⲁⲣⲭⲓⲉⲣⲉⲩⲥ -->
<feat xlink:href="#orig_13" value="ⲙⲛ"/><!-- ⲙⲛ -->
<feat xlink:href="#orig_14" value="ⲛⲉ"/><!-- ⲛⲉ -->
<feat xlink:href="#orig_15" value="ⲡⲣⲉⲥⲃⲩⲧⲉⲣⲟⲥ"/><!-- ⲡⲣⲉⲥⲃⲩⲧⲉⲣⲟⲥ -->
<feat xlink:href="#orig_16" value="ⲙⲛ"/><!-- ⲙⲛ -->
<feat xlink:href="#orig_17" value="ⲛⲉ"/><!-- ⲛⲉ -->
<feat xlink:href="#orig_18" value="ⲅⲣⲁⲙⲙⲁⲧⲉⲩⲥ"/><!-- ⲅⲣⲁⲙⲙⲁⲧⲉⲩⲥ -->
<feat xlink:href="#orig_19" value="ⲙⲛ"/><!-- ⲙⲛ -->
<feat xlink:href="#orig_20" value="ⲡ"/><!-- ⲡ -->
<feat xlink:href="#orig_21" value="ⲥⲩⲛϩⲉⲇⲣⲓⲟⲛ"/><!-- ⲥⲩⲛϩⲉⲇⲣⲓⲟⲛ -->
<feat xlink:href="#orig_22" value="ⲧⲏⲣ"/><!-- ⲧⲏⲣ -->
<feat xlink:href="#orig_23" value="ϥ"/><!-- ϥ -->
<feat xlink:href="#orig_24" value="ⲁⲩⲱ"/><!-- ⲁⲩⲱ -->
<feat xlink:href="#orig_25" value="ⲁ"/><!-- ⲁ -->
<feat xlink:href="#orig_26" value="ⲩ"/><!-- ⲩ -->
<feat xlink:href="#orig_27" value="ⲥⲉⲛϩ"/><!-- ⲥⲉⲛϩ -->
<feat xlink:href="#orig_28" value="ⲓⲏⲥⲟⲩⲥ"/><!-- ⲓⲏⲥⲟⲩⲥ -->
<feat xlink:href="#orig_29" value="ⲁ"/><!-- ⲁ -->
<feat xlink:href="#orig_30" value="ⲩ"/><!-- ⲩ -->
<feat xlink:href="#orig_31" value="ϫⲓⲧ"/><!-- ϫⲓⲧ -->
<feat xlink:href="#orig_32" value="ϥ"/><!-- ϥ -->
<feat xlink:href="#orig_33" value="ⲁ"/><!-- ⲁ -->
<feat xlink:href="#orig_34" value="ⲩ"/><!-- ⲩ -->
<feat xlink:href="#orig_35" value="ⲧⲁⲁ"/><!-- ⲧⲁⲁ -->
<feat xlink:href="#orig_36" value="ϥ"/><!-- ϥ -->
<feat xlink:href="#orig_37" value="ⲉⲧⲟⲟⲧ"/><!-- ⲉⲧⲟⲟⲧ -->
<feat xlink:href="#orig_38" value="ϥ"/><!-- ϥ -->
<feat xlink:href="#orig_39" value="ⲙ"/><!-- ⲙ -->
<feat xlink:href="#orig_40" value="ⲡⲓⲗⲁⲧⲟⲥ"/><!-- ⲡⲓⲗⲁⲧⲟⲥ -->
<feat xlink:href="#orig_41" value="."/><!-- . -->
<feat xlink:href="#orig_42" value="ⲁⲩⲱ"/><!-- ⲁⲩⲱ -->
<feat xlink:href="#orig_43" value="ⲁ"/><!-- ⲁ -->
<feat xlink:href="#orig_44" value="ⲡⲓⲗⲁⲧⲟⲥ"/><!-- ⲡⲓⲗⲁⲧⲟⲥ -->
<feat xlink:href="#orig_45" value="ϫⲛⲟⲩ"/><!-- ϫⲛⲟⲩ -->
<feat xlink:href="#orig_46" value="ϥ"/><!-- ϥ -->
<feat xlink:href="#orig_47" value="ϫⲉ"/><!-- ϫⲉ -->
<feat xlink:href="#orig_48" value="ⲛⲧⲟⲕ"/><!-- ⲛⲧⲟⲕ -->
<feat xlink:href="#orig_49" value="ⲡⲉ"/><!-- ⲡⲉ -->
<feat xlink:href="#orig_50" value="ⲡ"/><!-- ⲡ -->
<feat xlink:href="#orig_51" value="ⲣⲣⲟ"/><!-- ⲣⲣⲟ -->
<feat xlink:href="#orig_52" value="ⲛ"/><!-- ⲛ -->
<feat xlink:href="#orig_53" value="ⲓⲟⲩⲇⲁⲓ"/><!-- ⲓⲟⲩⲇⲁⲓ -->
<feat xlink:href="#orig_54" value="."/><!-- . -->
<feat xlink:href="#orig_55" value="ⲛⲧⲟϥ"/><!-- ⲛⲧⲟϥ -->
<feat xlink:href="#orig_56" value="ⲇⲉ"/><!-- ⲇⲉ -->
<feat xlink:href="#orig_57" value="ⲁ"/><!-- ⲁ -->
<feat xlink:href="#orig_58" value="ϥ"/><!-- ϥ -->
<feat xlink:href="#orig_59" value="ⲟⲩⲱϣⲃ"/><!-- ⲟⲩⲱϣⲃ -->
<feat xlink:href="#orig_60" value="ⲛⲁ"/><!-- ⲛⲁ -->
<feat xlink:href="#orig_61" value="ϥ"/><!-- ϥ -->
<feat xlink:href="#orig_62" value="ⲉ"/><!-- ⲉ -->
<feat xlink:href="#orig_63" value="ϥ"/><!-- ϥ -->
<feat xlink:href="#orig_64" value="ϫⲱ"/><!-- ϫⲱ -->
<feat xlink:href="#orig_65" value="ⲙⲙⲟ"/><!-- ⲙⲙⲟ -->
<feat xlink:href="#orig_66" value="ⲥ"/><!-- ⲥ -->
<feat xlink:href="#orig_67" value="ϫⲉ"/><!-- ϫⲉ -->
<feat xlink:href="#orig_68" value="ⲛⲧⲟⲕ"/><!-- ⲛⲧⲟⲕ -->
<feat xlink:href="#orig_69" value="ⲡ"/><!-- ⲡ -->
<feat xlink:href="#orig_70" value="ⲉⲧ"/><!-- ⲉⲧ -->
<feat xlink:href="#orig_71" value="ϫⲱ"/><!-- ϫⲱ -->
<feat xlink:href="#orig_72" value="ⲙⲙⲟ"/><!-- ⲙⲙⲟ -->
<feat xlink:href="#orig_73" value="ⲥ"/><!-- ⲥ -->
<feat xlink:href="#orig_74" value="."/><!-- . -->
<feat xlink:href="#orig_75" value="ⲁⲩⲱ"/><!-- ⲁⲩⲱ -->
<feat xlink:href="#orig_76" value="ⲛ"/><!-- ⲛ -->
<feat xlink:href="#orig_77" value="ⲁⲣⲭⲓⲉⲣⲉⲩⲥ"/><!-- ⲁⲣⲭⲓⲉⲣⲉⲩⲥ -->
<feat xlink:href="#orig_78" value="ⲁ"/><!-- ⲁ -->
<feat xlink:href="#orig_79" value="ⲩ"/><!-- ⲩ -->
<feat xlink:href="#orig_80" value="ⲕⲁⲧⲏⲅⲟⲣⲓ"/><!-- ⲕⲁⲧⲏⲅⲟⲣⲓ -->
<feat xlink:href="#orig_81" value="ⲙⲙⲟ"/><!-- ⲙⲙⲟ -->
<feat xlink:href="#orig_82" value="ϥ"/><!-- ϥ -->
<feat xlink:href="#orig_83" value="ⲉⲙⲁⲧⲉ"/><!-- ⲉⲙⲁⲧⲉ -->
<feat xlink:href="#orig_84" value="."/><!-- . -->
<feat xlink:href="#orig_85" value="ⲡⲓⲗⲁⲧⲟⲥ"/><!-- ⲡⲓⲗⲁⲧⲟⲥ -->
<feat xlink:href="#orig_86" value="ⲇⲉ"/><!-- ⲇⲉ -->
<feat xlink:href="#orig_87" value="ⲟⲛ"/><!-- ⲟⲛ -->
<feat xlink:href="#orig_88" value="ⲁ"/><!-- ⲁ -->
<feat xlink:href="#orig_89" value="ϥ"/><!-- ϥ -->
<feat xlink:href="#orig_90" value="ϫⲛⲟⲩ"/><!-- ϫⲛⲟⲩ -->
<feat xlink:href="#orig_91" value="ϥ"/><!-- ϥ -->
<feat xlink:href="#orig_92" value="ϫⲉ"/><!-- ϫⲉ -->
<feat xlink:href="#orig_93" value="ⲛ"/><!-- ⲛ -->
<feat xlink:href="#orig_94" value="ⲅ"/><!-- ⲅ -->
<feat xlink:href="#orig_95" value="ⲛⲁ"/><!-- ⲛⲁ -->
<feat xlink:href="#orig_96" value="ϣⲁϫⲉ"/><!-- ϣⲁϫⲉ -->
<feat xlink:href="#orig_97" value="ⲁⲛ"/><!-- ⲁⲛ -->
<feat xlink:href="#orig_98" value="ⲗⲁⲁⲩ"/><!-- ⲗⲁⲁⲩ -->
<feat xlink:href="#orig_99" value="."/><!-- . -->
<feat xlink:href="#orig_100" value="ⲁⲛⲁⲩ"/><!-- ⲁⲛⲁⲩ -->
<feat xlink:href="#orig_101" value="ϫⲉ"/><!-- ϫⲉ -->
<feat xlink:href="#orig_102" value="ⲥⲉ"/><!-- ⲥⲉ -->
<feat xlink:href="#orig_103" value="ⲣⲙⲛⲧⲣⲉ"/><!-- ⲣ...ⲙⲛⲧⲣⲉ -->
<feat xlink:href="#orig_105" value="ⲉⲣⲟ"/><!-- ⲉⲣⲟ -->
<feat xlink:href="#orig_106" value="ⲕ"/><!-- ⲕ -->
<feat xlink:href="#orig_107" value="ⲟⲩⲏⲣ"/><!-- ⲟⲩⲏⲣ -->
<feat xlink:href="#orig_108" value="."/><!-- . -->
<feat xlink:href="#orig_109" value="ⲓⲏⲥⲟⲩⲥ"/><!-- ⲓⲏⲥⲟⲩⲥ -->
<feat xlink:href="#orig_110" value="ⲇⲉ"/><!-- ⲇⲉ -->
<feat xlink:href="#orig_111" value="ⲙⲡ"/><!-- ⲙⲡ -->
<feat xlink:href="#orig_112" value="ϥ"/><!-- ϥ -->
<feat xlink:href="#orig_113" value="ϣⲁϫⲉ"/><!-- ϣⲁϫⲉ -->
<feat xlink:href="#orig_114" value="ⲗⲁⲁⲩ"/><!-- ⲗⲁⲁⲩ -->
<feat xlink:href="#orig_115" value="."/><!-- . -->
<feat xlink:href="#orig_116" value="ϩⲱⲥⲧⲉ"/><!-- ϩⲱⲥⲧⲉ -->
<feat xlink:href="#orig_117" value="ⲛⲧⲉ"/><!-- ⲛⲧⲉ -->
<feat xlink:href="#orig_118" value="ⲡⲓⲗⲁⲧⲟⲥ"/><!-- ⲡⲓⲗⲁⲧⲟⲥ -->
<feat xlink:href="#orig_119" value="ⲣϣⲡⲏⲣⲉ"/><!-- ⲣ...ϣⲡⲏⲣⲉ -->
<feat xlink:href="#orig_121" value="."/><!-- . -->
<feat xlink:href="#orig_122" value="ⲕⲁⲧⲁ"/><!-- ⲕⲁⲧⲁ -->
<feat xlink:href="#orig_123" value="ϣⲁ"/><!-- ϣⲁ -->
<feat xlink:href="#orig_124" value="ⲇⲉ"/><!-- ⲇⲉ -->
<feat xlink:href="#orig_125" value="ϣⲁ"/><!-- ϣⲁ -->
<feat xlink:href="#orig_126" value="ϥ"/><!-- ϥ -->
<feat xlink:href="#orig_127" value="ⲕⲱ"/><!-- ⲕⲱ -->
<feat xlink:href="#orig_128" value="ⲛⲁ"/><!-- ⲛⲁ -->
<feat xlink:href="#orig_129" value="ⲩ"/><!-- ⲩ -->
<feat xlink:href="#orig_130" value="ⲉⲃⲟⲗ"/><!-- ⲉⲃⲟⲗ -->
<feat xlink:href="#orig_131" value="ⲛ"/><!-- ⲛ -->
<feat xlink:href="#orig_132" value="ⲟⲩⲁ"/><!-- ⲟⲩⲁ -->
<feat xlink:href="#orig_133" value="ⲉ"/><!-- ⲉ -->
<feat xlink:href="#orig_134" value="ϥ"/><!-- ϥ -->
<feat xlink:href="#orig_135" value="ϭⲏⲡ"/><!-- ϭⲏⲡ -->
<feat xlink:href="#orig_136" value="ⲡ"/><!-- ⲡ -->
<feat xlink:href="#orig_137" value="ⲉⲧ"/><!-- ⲉⲧ -->
<feat xlink:href="#orig_138" value="ⲟⲩ"/><!-- ⲟⲩ -->
<feat xlink:href="#orig_139" value="ⲛⲁ"/><!-- ⲛⲁ -->
<feat xlink:href="#orig_140" value="ⲁⲓⲧⲓ"/><!-- ⲁⲓⲧⲓ -->
<feat xlink:href="#orig_141" value="ⲙⲙⲟ"/><!-- ⲙⲙⲟ -->
<feat xlink:href="#orig_142" value="ϥ"/><!-- ϥ -->
<feat xlink:href="#orig_143" value="."/><!-- . -->
<feat xlink:href="#orig_144" value="ⲛⲉ"/><!-- ⲛⲉ -->
<feat xlink:href="#orig_145" value="ϥ"/><!-- ϥ -->
<feat xlink:href="#orig_146" value="ϭⲏⲡ"/><!-- ϭⲏⲡ -->
<feat xlink:href="#orig_147" value="ⲇⲉ"/><!-- ⲇⲉ -->
<feat xlink:href="#orig_148" value="ⲛϭⲓ"/><!-- ⲛϭⲓ -->
<feat xlink:href="#orig_149" value="ⲡ"/><!-- ⲡ -->
<feat xlink:href="#orig_150" value="ⲉⲧⲉ"/><!-- ⲉⲧⲉ -->
<feat xlink:href="#orig_151" value="ϣⲁ"/><!-- ϣⲁ -->
<feat xlink:href="#orig_152" value="ⲩ"/><!-- ⲩ -->
<feat xlink:href="#orig_153" value="ⲙⲟⲩⲧⲉ"/><!-- ⲙⲟⲩⲧⲉ -->
<feat xlink:href="#orig_154" value="ⲉⲣⲟ"/><!-- ⲉⲣⲟ -->
<feat xlink:href="#orig_155" value="ϥ"/><!-- ϥ -->
<feat xlink:href="#orig_156" value="ϫⲉ"/><!-- ϫⲉ -->
<feat xlink:href="#orig_157" value="ⲃⲁⲣⲁⲃⲃⲁ"/><!-- ⲃⲁⲣⲁⲃⲃⲁ -->
<feat xlink:href="#orig_158" value="."/><!-- . -->
<feat xlink:href="#orig_159" value="ⲙⲛ"/><!-- ⲙⲛ -->
<feat xlink:href="#orig_160" value="ⲛ"/><!-- ⲛ -->
<feat xlink:href="#orig_161" value="ⲉⲛⲧ"/><!-- ⲉⲛⲧ -->
<feat xlink:href="#orig_162" value="ⲁ"/><!-- ⲁ -->
<feat xlink:href="#orig_163" value="ⲩ"/><!-- ⲩ -->
<feat xlink:href="#orig_164" value="ⲥⲧⲁⲥⲓⲁⲍⲉ"/><!-- ⲥⲧⲁⲥⲓⲁⲍⲉ -->
<feat xlink:href="#orig_165" value="."/><!-- . -->
<feat xlink:href="#orig_166" value="ⲛⲁⲓ"/><!-- ⲛⲁⲓ -->
<feat xlink:href="#orig_167" value="ⲛⲧ"/><!-- ⲛⲧ -->
<feat xlink:href="#orig_168" value="ⲁ"/><!-- ⲁ -->
<feat xlink:href="#orig_169" value="ⲩ"/><!-- ⲩ -->
<feat xlink:href="#orig_170" value="ⲣⲫⲟⲛⲟⲥ"/><!-- ⲣ...ⲫⲟⲛⲟⲥ -->
<feat xlink:href="#orig_172" value="ϩⲛ"/><!-- ϩⲛ -->
<feat xlink:href="#orig_173" value="ⲧⲉ"/><!-- ⲧⲉ -->
<feat xlink:href="#orig_174" value="ⲥⲧⲁⲥⲓⲥ"/><!-- ⲥⲧⲁⲥⲓⲥ -->
<feat xlink:href="#orig_175" value="."/><!-- . -->
<feat xlink:href="#orig_176" value="ⲁⲩⲱ"/><!-- ⲁⲩⲱ -->
<feat xlink:href="#orig_177" value="ⲡ"/><!-- ⲡ -->
<feat xlink:href="#orig_178" value="ⲙⲏⲏϣⲉ"/><!-- ⲙⲏⲏϣⲉ -->
<feat xlink:href="#orig_179" value="ⲛⲧⲉⲣⲉ"/><!-- ⲛⲧⲉⲣⲉ -->
<feat xlink:href="#orig_180" value="ϥ"/><!-- ϥ -->
<feat xlink:href="#orig_181" value="ⲃⲱⲕ"/><!-- ⲃⲱⲕ -->
<feat xlink:href="#orig_182" value="ⲉϩⲣⲁⲓ"/><!-- ⲉϩⲣⲁⲓ -->
<feat xlink:href="#orig_183" value="ⲁ"/><!-- ⲁ -->
<feat xlink:href="#orig_184" value="ϥ"/><!-- ϥ -->
<feat xlink:href="#orig_185" value="ⲁⲣⲭⲓ"/><!-- ⲁⲣⲭⲓ -->
<feat xlink:href="#orig_186" value="ⲛ"/><!-- ⲛ -->
<feat xlink:href="#orig_187" value="ⲁⲓⲧⲓ"/><!-- ⲁⲓⲧⲓ -->
<feat xlink:href="#orig_188" value="ⲕⲁⲧⲁ"/><!-- ⲕⲁⲧⲁ -->
<feat xlink:href="#orig_189" value="ⲧ"/><!-- ⲧ -->
<feat xlink:href="#orig_190" value="ϩⲉ"/><!-- ϩⲉ -->
<feat xlink:href="#orig_191" value="ⲛ"/><!-- ⲛ -->
<feat xlink:href="#orig_192" value="ϣⲁ"/><!-- ϣⲁ -->
<feat xlink:href="#orig_193" value="ϥ"/><!-- ϥ -->
<feat xlink:href="#orig_194" value="ⲁⲁ"/><!-- ⲁⲁ -->
<feat xlink:href="#orig_195" value="ⲥ"/><!-- ⲥ -->
<feat xlink:href="#orig_196" value="ⲛⲁ"/><!-- ⲛⲁ -->
<feat xlink:href="#orig_197" value="ⲩ"/><!-- ⲩ -->
<feat xlink:href="#orig_198" value="."/><!-- . -->
<feat xlink:href="#orig_199" value="ⲡⲓⲗⲁⲧⲟⲥ"/><!-- ⲡⲓⲗⲁⲧⲟⲥ -->
<feat xlink:href="#orig_200" value="ⲇⲉ"/><!-- ⲇⲉ -->
<feat xlink:href="#orig_201" value="ⲁ"/><!-- ⲁ -->
<feat xlink:href="#orig_202" value="ϥ"/><!-- ϥ -->
<feat xlink:href="#orig_203" value="ⲟⲩⲱϣⲃ"/><!-- ⲟⲩⲱϣⲃ -->
<feat xlink:href="#orig_204" value="ⲉ"/><!-- ⲉ -->
<feat xlink:href="#orig_205" value="ϥ"/><!-- ϥ -->
<feat xlink:href="#orig_206" value="ϫⲱ"/><!-- ϫⲱ -->
<feat xlink:href="#orig_207" value="ⲙⲙⲟ"/><!-- ⲙⲙⲟ -->
<feat xlink:href="#orig_208" value="ⲥ"/><!-- ⲥ -->
<feat xlink:href="#orig_209" value="ⲛⲁ"/><!-- ⲛⲁ -->
<feat xlink:href="#orig_210" value="ⲩ"/><!-- ⲩ -->
<feat xlink:href="#orig_211" value="ϫⲉ"/><!-- ϫⲉ -->
<feat xlink:href="#orig_212" value="ⲧⲉⲧⲛ"/><!-- ⲧⲉⲧⲛ -->
<feat xlink:href="#orig_213" value="ⲟⲩⲱϣ"/><!-- ⲟⲩⲱϣ -->
<feat xlink:href="#orig_214" value="ⲉ"/><!-- ⲉ -->
<feat xlink:href="#orig_215" value="ⲧⲣ"/><!-- ⲧⲣ -->
<feat xlink:href="#orig_216" value="ⲁ"/><!-- ⲁ -->
<feat xlink:href="#orig_217" value="ⲕⲱ"/><!-- ⲕⲱ -->
<feat xlink:href="#orig_218" value="ⲛⲏ"/><!-- ⲛⲏ -->
<feat xlink:href="#orig_219" value="ⲧⲛ"/><!-- ⲧⲛ -->
<feat xlink:href="#orig_220" value="ⲉⲃⲟⲗ"/><!-- ⲉⲃⲟⲗ -->
<feat xlink:href="#orig_221" value="ⲙ"/><!-- ⲙ -->
<feat xlink:href="#orig_222" value="ⲡⲉ"/><!-- ⲡⲉ -->
<feat xlink:href="#orig_223" value="ⲣⲟ"/><!-- ⲣⲟ -->
<feat xlink:href="#orig_224" value="ⲛ"/><!-- ⲛ -->
<feat xlink:href="#orig_225" value="ⲓⲟⲩⲇⲁⲓ"/><!-- ⲓⲟⲩⲇⲁⲓ -->
<feat xlink:href="#orig_226" value="ⲛⲉ"/><!-- ⲛⲉ -->
<feat xlink:href="#orig_227" value="ϥ"/><!-- ϥ -->
<feat xlink:href="#orig_228" value="ⲥⲟⲟⲩⲛ"/><!-- ⲥⲟⲟⲩⲛ -->
<feat xlink:href="#orig_229" value="ⲅⲁⲣ"/><!-- ⲅⲁⲣ -->
<feat xlink:href="#orig_230" value="ϫⲉ"/><!-- ϫⲉ -->
<feat xlink:href="#orig_231" value="ⲉⲧⲃⲉ"/><!-- ⲉⲧⲃⲉ -->
<feat xlink:href="#orig_232" value="ⲟⲩ"/><!-- ⲟⲩ -->
<feat xlink:href="#orig_233" value="ⲫⲑⲟⲛⲟⲥ"/><!-- ⲫⲑⲟⲛⲟⲥ -->
<feat xlink:href="#orig_234" value="ⲛⲧ"/><!-- ⲛⲧ -->
<feat xlink:href="#orig_235" value="ⲁ"/><!-- ⲁ -->
<feat xlink:href="#orig_236" value="ⲩ"/><!-- ⲩ -->
<feat xlink:href="#orig_237" value="ⲡⲁⲣⲁⲇⲓⲇⲟⲩ"/><!-- ⲡⲁⲣⲁⲇⲓⲇⲟⲩ -->
<feat xlink:href="#orig_238" value="ⲙⲙⲟ"/><!-- ⲙⲙⲟ -->
<feat xlink:href="#orig_239" value="ϥ"/><!-- ϥ -->
<feat xlink:href="#orig_240" value="ⲛϭⲓ"/><!-- ⲛϭⲓ -->
<feat xlink:href="#orig_241" value="ⲛ"/><!-- ⲛ -->
<feat xlink:href="#orig_242" value="ⲁⲣⲭⲓⲉⲣⲉⲩⲥ"/><!-- ⲁⲣⲭⲓⲉⲣⲉⲩⲥ -->
<feat xlink:href="#orig_243" value="ⲛ"/><!-- ⲛ -->
<feat xlink:href="#orig_244" value="ⲁⲣⲭⲓⲉⲣⲉⲩⲥ"/><!-- ⲁⲣⲭⲓⲉⲣⲉⲩⲥ -->
<feat xlink:href="#orig_245" value="ⲇⲉ"/><!-- ⲇⲉ -->
<feat xlink:href="#orig_246" value="ⲁ"/><!-- ⲁ -->
<feat xlink:href="#orig_247" value="ⲩ"/><!-- ⲩ -->
<feat xlink:href="#orig_248" value="ⲡⲓⲑⲉ"/><!-- ⲡⲓⲑⲉ -->
<feat xlink:href="#orig_249" value="ⲙ"/><!-- ⲙ -->
<feat xlink:href="#orig_250" value="ⲡ"/><!-- ⲡ -->
<feat xlink:href="#orig_251" value="ⲙⲏⲏϣⲉ"/><!-- ⲙⲏⲏϣⲉ -->
<feat xlink:href="#orig_252" value="ϫⲉⲕⲁⲁⲥ"/><!-- ϫⲉⲕⲁⲁⲥ -->
<feat xlink:href="#orig_253" value="ⲉ"/><!-- ⲉ -->
<feat xlink:href="#orig_254" value="ⲩ"/><!-- ⲩ -->
<feat xlink:href="#orig_255" value="ⲉ"/><!-- ⲉ -->
<feat xlink:href="#orig_256" value="ⲁⲓⲧⲓ"/><!-- ⲁⲓⲧⲓ -->
<feat xlink:href="#orig_257" value="ⲃ"/><!-- ⲃ -->
<feat xlink:href="#orig_258" value="ⲃⲁⲣⲁⲃⲃⲁⲥ"/><!-- ⲃⲁⲣⲁⲃⲃⲁⲥ -->
<feat xlink:href="#orig_259" value="ⲉ"/><!-- ⲉ -->
<feat xlink:href="#orig_260" value="ⲧⲣⲉ"/><!-- ⲧⲣⲉ -->
<feat xlink:href="#orig_261" value="ϥ"/><!-- ϥ -->
<feat xlink:href="#orig_262" value="ⲕⲁⲁ"/><!-- ⲕⲁⲁ -->
<feat xlink:href="#orig_263" value="ϥ"/><!-- ϥ -->
<feat xlink:href="#orig_264" value="ⲛⲁ"/><!-- ⲛⲁ -->
<feat xlink:href="#orig_265" value="ⲩ"/><!-- ⲩ -->
<feat xlink:href="#orig_266" value="ⲉⲃⲟⲗ"/><!-- ⲉⲃⲟⲗ -->
<feat xlink:href="#orig_267" value="."/><!-- . -->
<feat xlink:href="#orig_268" value="ⲡⲓⲗⲁⲧⲟⲥ"/><!-- ⲡⲓⲗⲁⲧⲟⲥ -->
<feat xlink:href="#orig_269" value="ⲇⲉ"/><!-- ⲇⲉ -->
<feat xlink:href="#orig_270" value="ⲟⲛ"/><!-- ⲟⲛ -->
<feat xlink:href="#orig_271" value="ⲁ"/><!-- ⲁ -->
<feat xlink:href="#orig_272" value="ϥ"/><!-- ϥ -->
<feat xlink:href="#orig_273" value="ⲟⲩⲱϣⲃ"/><!-- ⲟⲩⲱϣⲃ -->
<feat xlink:href="#orig_274" value="ⲉ"/><!-- ⲉ -->
<feat xlink:href="#orig_275" value="ϥ"/><!-- ϥ -->
<feat xlink:href="#orig_276" value="ϫⲱ"/><!-- ϫⲱ -->
<feat xlink:href="#orig_277" value="ⲙⲙⲟ"/><!-- ⲙⲙⲟ -->
<feat xlink:href="#orig_278" value="ⲥ"/><!-- ⲥ -->
<feat xlink:href="#orig_279" value="ⲛⲁ"/><!-- ⲛⲁ -->
<feat xlink:href="#orig_280" value="ⲩ"/><!-- ⲩ -->
<feat xlink:href="#orig_281" value="ϫⲉ"/><!-- ϫⲉ -->
<feat xlink:href="#orig_282" value="ⲁϫⲓ"/><!-- ⲁϫⲓ -->
<feat xlink:href="#orig_283" value="ⲥ"/><!-- ⲥ -->
<feat xlink:href="#orig_284" value="ⲛⲁ"/><!-- ⲛⲁ -->
<feat xlink:href="#orig_285" value="ⲓ"/><!-- ⲓ -->
<feat xlink:href="#orig_286" value="ϫⲉ"/><!-- ϫⲉ -->
<feat xlink:href="#orig_287" value="ⲧⲁ"/><!-- ⲧⲁ -->
<feat xlink:href="#orig_288" value="ⲣ"/><!-- ⲣ -->
<feat xlink:href="#orig_289" value="ⲟⲩ"/><!-- ⲟⲩ -->
<feat xlink:href="#orig_290" value="ϭⲉ"/><!-- ϭⲉ -->
<feat xlink:href="#orig_291" value="ⲙ"/><!-- ⲙ -->
<feat xlink:href="#orig_292" value="ⲡⲉ"/><!-- ⲡⲉ -->
<feat xlink:href="#orig_293" value="ⲣⲟ"/><!-- ⲣⲟ -->
<feat xlink:href="#orig_294" value="ⲛ"/><!-- ⲛ -->
<feat xlink:href="#orig_295" value="ⲓⲟⲩⲇⲁⲓ"/><!-- ⲓⲟⲩⲇⲁⲓ -->
<feat xlink:href="#orig_296" value="ⲛⲧⲟⲟⲩ"/><!-- ⲛⲧⲟⲟⲩ -->
<feat xlink:href="#orig_297" value="ⲇⲉ"/><!-- ⲇⲉ -->
<feat xlink:href="#orig_298" value="ⲟⲛ"/><!-- ⲟⲛ -->
<feat xlink:href="#orig_299" value="ⲁ"/><!-- ⲁ -->
<feat xlink:href="#orig_300" value="ⲩ"/><!-- ⲩ -->
<feat xlink:href="#orig_301" value="ϫⲓϣⲕⲁⲕ"/><!-- ϫⲓ...ϣⲕⲁⲕ -->
<feat xlink:href="#orig_303" value="ⲉⲃⲟⲗ"/><!-- ⲉⲃⲟⲗ -->
<feat xlink:href="#orig_304" value="ϫⲉ"/><!-- ϫⲉ -->
<feat xlink:href="#orig_305" value="ⲥⲧⲁⲩⲣⲟⲩ"/><!-- ⲥⲧⲁⲩⲣⲟⲩ -->
<feat xlink:href="#orig_306" value="ⲙⲙⲟ"/><!-- ⲙⲙⲟ -->
<feat xlink:href="#orig_307" value="ϥ"/><!-- ϥ -->
<feat xlink:href="#orig_308" value="."/><!-- . -->
<feat xlink:href="#orig_309" value="["/><!-- [ -->
<feat xlink:href="#orig_310" value="ⲡⲉϫⲉ"/><!-- ⲡⲉϫⲉ -->
<feat xlink:href="#orig_311" value="ⲡⲓⲗⲁⲧⲟⲥ"/><!-- ⲡⲓⲗⲁⲧⲟⲥ -->
<feat xlink:href="#orig_312" value="ⲇⲉ"/><!-- ⲇⲉ -->
<feat xlink:href="#orig_313" value="ⲛⲁ"/><!-- ⲛⲁ -->
<feat xlink:href="#orig_314" value="ⲩ"/><!-- ⲩ -->
<feat xlink:href="#orig_315" value="ϫⲉ"/><!-- ϫⲉ -->
<feat xlink:href="#orig_316" value="ⲟⲩ"/><!-- ⲟⲩ -->
<feat xlink:href="#orig_317" value="ⲡⲉ"/><!-- ⲡⲉ -->
<feat xlink:href="#orig_318" value="ⲡ"/><!-- ⲡ -->
<feat xlink:href="#orig_319" value="ⲡ"/><!-- ⲡ -->
<feat xlink:href="#orig_320" value="ⲉ"/><!-- ⲉ -->
<feat xlink:href="#orig_321" value="ⲑⲟⲟⲯ"/><!-- ⲑⲟⲟⲯ -->
<feat xlink:href="#orig_322" value="ⲛⲧ"/><!-- ⲛⲧ -->
<feat xlink:href="#orig_323" value="ⲁ"/><!-- ⲁ -->
<feat xlink:href="#orig_324" value="ϥ"/><!-- ϥ -->
<feat xlink:href="#orig_325" value="ⲁⲁ"/><!--  -->
<feat xlink:href="#orig_326" value="ϥ"/><!-- ⲁⲁϥ -->
<feat xlink:href="#orig_327" value="."/><!-- . -->
<feat xlink:href="#orig_328" value="ⲛⲧⲟⲟⲩ"/><!-- ⲛⲧⲟⲟⲩ -->
<feat xlink:href="#orig_329" value="ⲇⲉ"/><!-- ⲇⲉ -->
<feat xlink:href="#orig_330" value="ⲛ"/><!-- ⲛ -->
<feat xlink:href="#orig_331" value="ϩⲟⲩⲟ"/><!-- ϩⲟⲩⲟ -->
<feat xlink:href="#orig_332" value="ⲁ"/><!-- ⲁ -->
<feat xlink:href="#orig_333" value="ⲩ"/><!-- ⲩ -->
<feat xlink:href="#orig_334" value="ϫⲓϣⲕⲁⲕ"/><!-- ϫⲓ...ϣⲕⲁⲕ -->
<feat xlink:href="#orig_336" value="ⲉⲃⲟⲗ"/><!-- ⲉⲃⲟⲗ -->
<feat xlink:href="#orig_337" value="ⲉ"/><!-- ⲉ -->
<feat xlink:href="#orig_338" value="ⲩ"/><!-- ⲩ -->
<feat xlink:href="#orig_339" value="ϫⲱ"/><!-- ϫⲱ -->
<feat xlink:href="#orig_340" value="ⲙⲙⲟ"/><!-- ⲙⲙⲟ -->
<feat xlink:href="#orig_341" value="ⲥ"/><!-- ⲥ -->
<feat xlink:href="#orig_342" value="ϫⲉ"/><!-- ϫⲉ -->
<feat xlink:href="#orig_343" value="ⲥⲧⲁⲩⲣⲟⲩ"/><!-- ⲥⲧⲁⲩⲣⲟⲩ -->
<feat xlink:href="#orig_344" value="ⲙⲙⲟ"/><!-- ⲙⲙⲟ -->
<feat xlink:href="#orig_345" value="ϥ"/><!-- ϥ -->
<feat xlink:href="#orig_346" value="."/><!-- . -->
<feat xlink:href="#orig_347" value="]"/><!-- ] -->
<feat xlink:href="#orig_348" value="ⲡⲓⲗⲁⲧⲟⲥ"/><!-- ⲡⲓⲗⲁⲧⲟⲥ -->
<feat xlink:href="#orig_349" value="ⲇⲉ"/><!-- ⲇⲉ -->
<feat xlink:href="#orig_350" value="ⲉ"/><!-- ⲉ -->
<feat xlink:href="#orig_351" value="ϥ"/><!-- ϥ -->
<feat xlink:href="#orig_352" value="ⲟⲩⲱϣ"/><!-- ⲟⲩⲱϣ -->
<feat xlink:href="#orig_353" value="ⲉ"/><!-- ⲉ -->
<feat xlink:href="#orig_354" value="ⲣⲡⲓⲑⲉ"/><!-- ⲣ...ⲡⲓⲑⲉ -->
<feat xlink:href="#orig_356" value="ⲙ"/><!-- ⲙ -->
<feat xlink:href="#orig_357" value="ⲡ"/><!-- ⲡ -->
<feat xlink:href="#orig_358" value="ⲙⲏⲏϣⲉ"/><!-- ⲙⲏⲏϣⲉ -->
<feat xlink:href="#orig_359" value="ⲁ"/><!-- ⲁ -->
<feat xlink:href="#orig_360" value="ϥ"/><!-- ϥ -->
<feat xlink:href="#orig_361" value="ⲕⲁ"/><!-- ⲕⲁ -->
<feat xlink:href="#orig_362" value="ⲃⲁⲣⲁⲃⲃⲁⲥ"/><!-- ⲃⲁⲣⲁⲃⲃⲁⲥ -->
<feat xlink:href="#orig_363" value="ⲛⲁ"/><!-- ⲛⲁ -->
<feat xlink:href="#orig_364" value="ⲩ"/><!-- ⲩ -->
<feat xlink:href="#orig_365" value="ⲉⲃⲟⲗ"/><!-- ⲉⲃⲟⲗ -->
<feat xlink:href="#orig_366" value="."/><!-- . -->
<feat xlink:href="#orig_367" value="ⲓⲏⲥⲟⲩⲥ"/><!-- ⲓⲏⲥⲟⲩⲥ -->
<feat xlink:href="#orig_368" value="ⲇⲉ"/><!-- ⲇⲉ -->
<feat xlink:href="#orig_369" value="ⲁ"/><!-- ⲁ -->
<feat xlink:href="#orig_370" value="ϥ"/><!-- ϥ -->
<feat xlink:href="#orig_371" value="ⲫⲣⲁⲅⲉⲗⲗⲟⲩ"/><!-- ⲫⲣⲁⲅⲉⲗⲗⲟⲩ -->
<feat xlink:href="#orig_372" value="ⲙⲙⲟ"/><!-- ⲙⲙⲟ -->
<feat xlink:href="#orig_373" value="ϥ"/><!-- ϥ -->
<feat xlink:href="#orig_374" value="ⲁ"/><!-- ⲁ -->
<feat xlink:href="#orig_375" value="ϥ"/><!-- ϥ -->
<feat xlink:href="#orig_376" value="ⲡⲁⲣⲁⲇⲓⲇⲟⲩ"/><!-- ⲡⲁⲣⲁⲇⲓⲇⲟⲩ -->
<feat xlink:href="#orig_377" value="ⲙⲙⲟ"/><!-- ⲙⲙⲟ -->
<feat xlink:href="#orig_378" value="ϥ"/><!-- ϥ -->
<feat xlink:href="#orig_379" value="ⲉ"/><!-- ⲉ -->
<feat xlink:href="#orig_380" value="ⲧⲣⲉ"/><!-- ⲧⲣⲉ -->
<feat xlink:href="#orig_381" value="ⲩ"/><!-- ⲩ -->
<feat xlink:href="#orig_382" value="ⲥⲧⲁⲩⲣⲟⲩ"/><!-- ⲥⲧⲁⲩⲣⲟⲩ -->
<feat xlink:href="#orig_383" value="ⲙⲙⲟ"/><!-- ⲙⲙⲟ -->
<feat xlink:href="#orig_384" value="ϥ"/><!-- ϥ -->
<feat xlink:href="#orig_385" value="."/><!-- . -->
<feat xlink:href="#orig_386" value="ⲙ"/><!-- ⲙ -->
<feat xlink:href="#orig_387" value="ⲙⲁⲧⲟⲓ"/><!-- ⲙⲁⲧⲟⲓ -->
<feat xlink:href="#orig_388" value="ⲇⲉ"/><!-- ⲇⲉ -->
<feat xlink:href="#orig_389" value="ⲁ"/><!-- ⲁ -->
<feat xlink:href="#orig_390" value="ⲩ"/><!-- ⲩ -->
<feat xlink:href="#orig_391" value="ϫⲓⲧ"/><!-- ϫⲓⲧ -->
<feat xlink:href="#orig_392" value="ϥ"/><!-- ϥ -->
<feat xlink:href="#orig_393" value="ⲉϩⲟⲩⲛ"/><!-- ⲉϩⲟⲩⲛ -->
<feat xlink:href="#orig_394" value="ⲉ"/><!-- ⲉ -->
<feat xlink:href="#orig_395" value="ⲧ"/><!-- ⲧ -->
<feat xlink:href="#orig_396" value="ⲁⲩⲗⲏ"/><!-- ⲁⲩⲗⲏ -->
<feat xlink:href="#orig_397" value="ⲉⲧⲉ"/><!-- ⲉⲧⲉ -->
<feat xlink:href="#orig_398" value="ⲡⲉ"/><!-- ⲡⲉ -->
<feat xlink:href="#orig_399" value="ⲡⲣⲁⲓⲧⲱⲣⲓⲟⲛ"/><!-- ⲡⲣⲁⲓⲧⲱⲣⲓⲟⲛ -->
<feat xlink:href="#orig_400" value="ⲡⲉ"/><!-- ⲡⲉ -->
<feat xlink:href="#orig_401" value="ⲁⲩⲱ"/><!-- ⲁⲩⲱ -->
<feat xlink:href="#orig_402" value="ⲁ"/><!-- ⲁ -->
<feat xlink:href="#orig_403" value="ⲩ"/><!-- ⲩ -->
<feat xlink:href="#orig_404" value="ⲥⲱⲟⲩϩ"/><!-- ⲥⲱⲟⲩϩ -->
<feat xlink:href="#orig_405" value="ⲉⲣⲟ"/><!-- ⲉⲣⲟ -->
<feat xlink:href="#orig_406" value="ϥ"/><!-- ϥ -->
<feat xlink:href="#orig_407" value="ⲛ"/><!-- ⲛ -->
<feat xlink:href="#orig_408" value="ⲧⲉ"/><!-- ⲧⲉ -->
<feat xlink:href="#orig_409" value="ⲥⲡⲓⲣⲁ"/><!-- ⲥⲡⲓⲣⲁ -->
<feat xlink:href="#orig_410" value="ⲧⲏⲣ"/><!-- ⲧⲏⲣ -->
<feat xlink:href="#orig_411" value="ⲥ"/><!-- ⲥ -->
<feat xlink:href="#orig_412" value="ⲁⲩⲱ"/><!-- ⲁⲩⲱ -->
<feat xlink:href="#orig_413" value="ⲁ"/><!-- ⲁ -->
<feat xlink:href="#orig_414" value="ⲩ"/><!-- ⲩ -->
<feat xlink:href="#orig_415" value="ϯ"/><!-- ϯ -->
<feat xlink:href="#orig_416" value="ϩⲓⲱⲱ"/><!-- ϩⲓⲱⲱ -->
<feat xlink:href="#orig_417" value="ϥ"/><!-- ϥ -->
<feat xlink:href="#orig_418" value="ⲛ"/><!-- ⲛ -->
<feat xlink:href="#orig_419" value="ⲟⲩ"/><!-- ⲟⲩ -->
<feat xlink:href="#orig_420" value="ⲭⲗⲁⲙⲩⲥ"/><!-- ⲭⲗⲁⲙⲩⲥ -->
<feat xlink:href="#orig_421" value="ⲛ"/><!-- ⲛ -->
<feat xlink:href="#orig_422" value="ϫⲏϭⲉ"/><!-- ϫⲏϭⲉ -->
<feat xlink:href="#orig_423" value="ⲁⲩⲱ"/><!-- ⲁⲩⲱ -->
<feat xlink:href="#orig_424" value="ⲁ"/><!-- ⲁ -->
<feat xlink:href="#orig_425" value="ⲩ"/><!-- ⲩ -->
<feat xlink:href="#orig_426" value="ϣⲛⲧ"/><!-- ϣⲛⲧ -->
<feat xlink:href="#orig_427" value="ⲟⲩ"/><!-- ⲟⲩ -->
<feat xlink:href="#orig_428" value="ⲕⲗⲟⲙ"/><!-- ⲕⲗⲟⲙ -->
<feat xlink:href="#orig_429" value="ⲛ"/><!-- ⲛ -->
<feat xlink:href="#orig_430" value="ϣⲟⲛⲧⲉ"/><!-- ϣⲟⲛⲧⲉ -->
<feat xlink:href="#orig_431" value="ⲁ"/><!-- ⲁ -->
<feat xlink:href="#orig_432" value="ⲩ"/><!-- ⲩ -->
<feat xlink:href="#orig_433" value="ⲕⲁⲁ"/><!-- ⲕⲁⲁ -->
<feat xlink:href="#orig_434" value="ϥ"/><!-- ϥ -->
<feat xlink:href="#orig_435" value="ϩⲓϫⲱ"/><!-- ϩⲓϫⲱ -->
<feat xlink:href="#orig_436" value="ϥ"/><!-- ϥ -->
<feat xlink:href="#orig_437" value="ⲁⲩⲱ"/><!-- ⲁⲩⲱ -->
<feat xlink:href="#orig_438" value="ⲁ"/><!-- ⲁ -->
<feat xlink:href="#orig_439" value="ⲩ"/><!-- ⲩ -->
<feat xlink:href="#orig_440" value="ⲁⲣⲭⲓ"/><!-- ⲁⲣⲭⲓ -->
<feat xlink:href="#orig_441" value="ⲛ"/><!-- ⲛ -->
<feat xlink:href="#orig_442" value="ⲁⲥⲡⲁⲍⲉ"/><!-- ⲁⲥⲡⲁⲍⲉ -->
<feat xlink:href="#orig_443" value="ⲙⲙⲟ"/><!-- ⲙⲙⲟ -->
<feat xlink:href="#orig_444" value="ϥ"/><!-- ϥ -->
<feat xlink:href="#orig_445" value="."/><!-- . -->
<feat xlink:href="#orig_446" value="ϫⲉ"/><!-- ϫⲉ -->
<feat xlink:href="#orig_447" value="ⲭⲁⲓⲣⲉ"/><!-- ⲭⲁⲓⲣⲉ -->
<feat xlink:href="#orig_448" value="ⲡ"/><!-- ⲡ -->
<feat xlink:href="#orig_449" value="ⲣⲣⲟ"/><!-- ⲣⲣⲟ -->
<feat xlink:href="#orig_450" value="ⲛ"/><!-- ⲛ -->
<feat xlink:href="#orig_451" value="ⲓⲟⲩⲇⲁⲓ"/><!-- ⲓⲟⲩⲇⲁⲓ -->
<feat xlink:href="#orig_452" value="."/><!-- . -->
<feat xlink:href="#orig_453" value="ⲁⲩⲱ"/><!-- ⲁⲩⲱ -->
<feat xlink:href="#orig_454" value="ⲁ"/><!-- ⲁ -->
<feat xlink:href="#orig_455" value="ⲩ"/><!-- ⲩ -->
<feat xlink:href="#orig_456" value="ϩⲓⲟⲩⲉ"/><!-- ϩⲓⲟⲩⲉ -->
<feat xlink:href="#orig_457" value="ⲙ"/><!-- ⲙ -->
<feat xlink:href="#orig_458" value="ⲡ"/><!-- ⲡ -->
<feat xlink:href="#orig_459" value="ⲕⲁϣ"/><!-- ⲕⲁϣ -->
<feat xlink:href="#orig_460" value="ⲉϫⲛ"/><!-- ⲉϫⲛ -->
<feat xlink:href="#orig_461" value="ⲧⲉϥ"/><!-- ⲧⲉϥ -->
<feat xlink:href="#orig_462" value="ⲁⲡⲉ"/><!-- ⲁⲡⲉ -->
<feat xlink:href="#orig_463" value="ⲁ"/><!-- ⲁ -->
<feat xlink:href="#orig_464" value="ⲩ"/><!-- ⲩ -->
<feat xlink:href="#orig_465" value="ⲛⲉϫ"/><!-- ⲛⲉϫ -->
<feat xlink:href="#orig_466" value="ⲧⲁϥ"/><!-- ⲧⲁϥ -->
<feat xlink:href="#orig_467" value="ⲉϩⲟⲩⲛ"/><!-- ⲉϩⲟⲩⲛ -->
<feat xlink:href="#orig_468" value="ⲉϩⲣⲁ"/><!-- ⲉϩⲣⲁ -->
<feat xlink:href="#orig_469" value="ϥ"/><!-- ϥ -->
<feat xlink:href="#orig_470" value="."/><!-- . -->
<feat xlink:href="#orig_471" value="ⲁⲩⲱ"/><!-- ⲁⲩⲱ -->
<feat xlink:href="#orig_472" value="ⲁ"/><!-- ⲁ -->
<feat xlink:href="#orig_473" value="ⲩ"/><!-- ⲩ -->
<feat xlink:href="#orig_474" value="ⲕⲗϫ"/><!-- ⲕⲗϫ -->
<feat xlink:href="#orig_475" value="ⲛⲉⲩ"/><!-- ⲛⲉⲩ -->
<feat xlink:href="#orig_476" value="ⲡⲁⲧ"/><!-- ⲡⲁⲧ -->
<feat xlink:href="#orig_477" value="ϩⲓϩⲏ"/><!-- ϩⲓϩⲏ -->
<feat xlink:href="#orig_478" value="ⲙⲙⲟ"/><!-- ⲙⲙⲟ -->
<feat xlink:href="#orig_479" value="ϥ"/><!-- ϥ -->
<feat xlink:href="#orig_480" value="ⲁ"/><!-- ⲁ -->
<feat xlink:href="#orig_481" value="ⲩ"/><!-- ⲩ -->
<feat xlink:href="#orig_482" value="ⲟⲩⲱϣⲧ"/><!-- ⲟⲩⲱϣⲧ -->
<feat xlink:href="#orig_483" value="ⲛⲁ"/><!-- ⲛⲁ -->
<feat xlink:href="#orig_484" value="ϥ"/><!-- ϥ -->
<feat xlink:href="#orig_485" value="."/><!-- . -->
<feat xlink:href="#orig_486" value="ⲛⲧⲉⲣ"/><!-- ⲛⲧⲉⲣ -->
<feat xlink:href="#orig_487" value="ⲟⲩ"/><!-- ⲟⲩ -->
<feat xlink:href="#orig_488" value="ⲱ"/><!-- ⲱ -->
<feat xlink:href="#orig_489" value="ⲇⲉ"/><!-- ⲇⲉ -->
<feat xlink:href="#orig_490" value="ⲉ"/><!-- ⲉ -->
<feat xlink:href="#orig_491" value="ⲩ"/><!-- ⲩ -->
<feat xlink:href="#orig_492" value="ⲥⲱⲃⲉ"/><!-- ⲥⲱⲃⲉ -->
<feat xlink:href="#orig_493" value="ⲙⲙⲟ"/><!-- ⲙⲙⲟ -->
<feat xlink:href="#orig_494" value="ϥ"/><!-- ϥ -->
<feat xlink:href="#orig_495" value="ⲁ"/><!-- ⲁ -->
<feat xlink:href="#orig_496" value="ⲩ"/><!-- ⲩ -->
<feat xlink:href="#orig_497" value="ⲕⲁⲁ"/><!-- ⲕⲁⲁ -->
<feat xlink:href="#orig_498" value="ϥ"/><!-- ϥ -->
<feat xlink:href="#orig_499" value="ⲕⲁϩⲏⲩ"/><!-- ⲕⲁϩⲏⲩ -->
<feat xlink:href="#orig_500" value="ⲛ"/><!-- ⲛ -->
<feat xlink:href="#orig_501" value="ⲧⲉ"/><!-- ⲧⲉ -->
<feat xlink:href="#orig_502" value="ⲭⲗⲁⲙⲩⲥ"/><!-- ⲭⲗⲁⲙⲩⲥ -->
<feat xlink:href="#orig_503" value="ⲛ"/><!-- ⲛ -->
<feat xlink:href="#orig_504" value="ϫⲏϭⲉ"/><!-- ϫⲏϭⲉ -->
<feat xlink:href="#orig_505" value="."/><!-- . -->
<feat xlink:href="#orig_506" value="ⲁ"/><!-- ⲁ -->
<feat xlink:href="#orig_507" value="ⲩ"/><!-- ⲩ -->
<feat xlink:href="#orig_508" value="ϯ"/><!-- ϯ -->
<feat xlink:href="#orig_509" value="ⲛⲉϥ"/><!-- ⲛⲉϥ -->
<feat xlink:href="#orig_510" value="ϩⲟⲓⲧⲉ"/><!-- ϩⲟⲓⲧⲉ -->
<feat xlink:href="#orig_511" value="ϩⲓⲱⲱ"/><!-- ϩⲓⲱⲱ -->
<feat xlink:href="#orig_512" value="ϥ"/><!-- ϥ -->
<feat xlink:href="#orig_513" value="ⲁⲩⲱ"/><!-- ⲁⲩⲱ -->
<feat xlink:href="#orig_514" value="ⲁ"/><!-- ⲁ -->
<feat xlink:href="#orig_515" value="ⲩ"/><!-- ⲩ -->
<feat xlink:href="#orig_516" value="ⲛⲧ"/><!-- ⲛⲧ -->
<feat xlink:href="#orig_517" value="ϥ"/><!-- ϥ -->
<feat xlink:href="#orig_518" value="ⲉⲃⲟⲗ"/><!-- ⲉⲃⲟⲗ -->
<feat xlink:href="#orig_519" value="ϫⲉ"/><!-- ϫⲉ -->
<feat xlink:href="#orig_520" value="ⲉ"/><!-- ⲉ -->
<feat xlink:href="#orig_521" value="ⲩ"/><!-- ⲩ -->
<feat xlink:href="#orig_522" value="ⲉ"/><!-- ⲉ -->
<feat xlink:href="#orig_523" value="ⲥⲧⲁⲩⲣⲟⲩ"/><!-- ⲥⲧⲁⲩⲣⲟⲩ -->
<feat xlink:href="#orig_524" value="ⲙⲙⲟ"/><!-- ⲙⲙⲟ -->
<feat xlink:href="#orig_525" value="ϥ"/><!-- ϥ -->
<feat xlink:href="#orig_526" value="."/><!-- . -->
<feat xlink:href="#orig_527" value="ⲁ"/><!-- ⲁ -->
<feat xlink:href="#orig_528" value="ⲩ"/><!-- ⲩ -->
<feat xlink:href="#orig_529" value="ⲕⲉϥⲉ"/><!-- ⲕⲉϥⲉ -->
<feat xlink:href="#orig_530" value="ⲟⲩⲁ"/><!-- ⲟⲩⲁ -->
<feat xlink:href="#orig_531" value="ⲇⲉ"/><!-- ⲇⲉ -->
<feat xlink:href="#orig_532" value="ⲉ"/><!-- ⲉ -->
<feat xlink:href="#orig_533" value="ϥ"/><!-- ϥ -->
<feat xlink:href="#orig_534" value="ⲙⲟⲟϣⲉ"/><!-- ⲙⲟⲟϣⲉ -->
<feat xlink:href="#orig_535" value="ⲉ"/><!-- ⲉ -->
<feat xlink:href="#orig_536" value="ⲡⲉϥ"/><!-- ⲡⲉϥ -->
<feat xlink:href="#orig_537" value="ⲣⲁⲛ"/><!-- ⲣⲁⲛ -->
<feat xlink:href="#orig_538" value="ⲡⲉ"/><!-- ⲡⲉ -->
<feat xlink:href="#orig_539" value="ⲥⲓⲙⲱⲛ"/><!-- ⲥⲓⲙⲱⲛ -->
<feat xlink:href="#orig_540" value="ⲡ"/><!-- ⲡ -->
<feat xlink:href="#orig_541" value="ⲕⲩⲣⲏⲛⲁⲓⲟⲥ"/><!-- ⲕⲩⲣⲏⲛⲁⲓⲟⲥ -->
<feat xlink:href="#orig_542" value="ⲉ"/><!-- ⲉ -->
<feat xlink:href="#orig_543" value="ϥ"/><!-- ϥ -->
<feat xlink:href="#orig_544" value="ⲛⲏⲩ"/><!-- ⲛⲏⲩ -->
<feat xlink:href="#orig_545" value="ⲉϩⲣⲁⲓ"/><!-- ⲉϩⲣⲁⲓ -->
<feat xlink:href="#orig_546" value="ϩⲛ"/><!-- ϩⲛ -->
<feat xlink:href="#orig_547" value="ⲧ"/><!-- ⲧ -->
<feat xlink:href="#orig_548" value="ⲥⲱϣⲉ"/><!-- ⲥⲱϣⲉ -->
<feat xlink:href="#orig_549" value="ⲡ"/><!-- ⲡ -->
<feat xlink:href="#orig_550" value="ⲓⲱⲧ"/><!-- ⲓⲱⲧ -->
<feat xlink:href="#orig_551" value="ⲛ"/><!-- ⲛ -->
<feat xlink:href="#orig_552" value="ⲁⲗⲉⲝⲁⲛⲇⲣⲟⲥ"/><!-- ⲁⲗⲉⲝⲁⲛⲇⲣⲟⲥ -->
<feat xlink:href="#orig_553" value="ⲙⲛ"/><!-- ⲙⲛ -->
<feat xlink:href="#orig_554" value="ϩⲣⲟⲩⲫⲟⲥ"/><!-- ϩⲣⲟⲩⲫⲟⲥ -->
<feat xlink:href="#orig_555" value="ϫⲉ"/><!-- ϫⲉ -->
<feat xlink:href="#orig_556" value="ⲉϥⲉ"/><!-- ⲉϥⲉ -->
<feat xlink:href="#orig_557" value="ϥⲓ"/><!-- ϥⲓ -->
<feat xlink:href="#orig_558" value="ⲡⲉϥ"/><!-- ⲡⲉϥ -->
<feat xlink:href="#orig_559" value="ⲥⲧⲁⲩⲣⲟⲥ"/><!-- ⲥⲧⲁⲩⲣⲟⲥ -->
<feat xlink:href="#orig_560" value="ⲁⲩⲱ"/><!-- ⲁⲩⲱ -->
<feat xlink:href="#orig_561" value="ⲁ"/><!-- ⲁ -->
<feat xlink:href="#orig_562" value="ϥ"/><!-- ϥ -->
<feat xlink:href="#orig_563" value="ⲛⲧ"/><!-- ⲛⲧ -->
<feat xlink:href="#orig_564" value="ϥ"/><!-- ϥ -->
<feat xlink:href="#orig_565" value="ⲉϩⲣⲁⲓ"/><!-- ⲉϩⲣⲁⲓ -->
<feat xlink:href="#orig_566" value="ⲉ"/><!-- ⲉ -->
<feat xlink:href="#orig_567" value="ⲡ"/><!-- ⲡ -->
<feat xlink:href="#orig_568" value="ⲙⲁ"/><!-- ⲙⲁ -->
<feat xlink:href="#orig_569" value="ϫⲉ"/><!-- ϫⲉ -->
<feat xlink:href="#orig_570" value="ⲅⲟⲗⲅⲟⲑⲁ"/><!-- ⲅⲟⲗⲅⲟⲑⲁ -->
<feat xlink:href="#orig_571" value="ⲡⲁⲓ"/><!-- ⲡⲁⲓ -->
<feat xlink:href="#orig_572" value="ⲉ"/><!-- ⲉ -->
<feat xlink:href="#orig_573" value="ϣⲁ"/><!-- ϣⲁ -->
<feat xlink:href="#orig_574" value="ⲩ"/><!-- ⲩ -->
<feat xlink:href="#orig_575" value="ϩⲉⲣⲙⲏⲛⲉⲩⲉ"/><!-- ϩⲉⲣⲙⲏⲛⲉⲩⲉ -->
<feat xlink:href="#orig_576" value="ⲙⲙⲟ"/><!-- ⲙⲙⲟ -->
<feat xlink:href="#orig_577" value="ϥ"/><!-- ϥ -->
<feat xlink:href="#orig_578" value="ϫⲉ"/><!-- ϫⲉ -->
<feat xlink:href="#orig_579" value="ⲡ"/><!-- ⲡ -->
<feat xlink:href="#orig_580" value="ⲧⲟⲡⲟⲥ"/><!-- ⲧⲟⲡⲟⲥ -->
<feat xlink:href="#orig_581" value="ⲙ"/><!-- ⲙ -->
<feat xlink:href="#orig_582" value="ⲡⲉ"/><!-- ⲡⲉ -->
<feat xlink:href="#orig_583" value="ⲕⲣⲁⲛⲓⲟⲛ"/><!-- ⲕⲣⲁⲛⲓⲟⲛ -->
<feat xlink:href="#orig_584" value="ⲁⲩⲱ"/><!-- ⲁⲩⲱ -->
<feat xlink:href="#orig_585" value="ⲁ"/><!-- ⲁ -->
<feat xlink:href="#orig_586" value="ⲩ"/><!-- ⲩ -->
<feat xlink:href="#orig_587" value="ϯ"/><!-- ϯ -->
<feat xlink:href="#orig_588" value="ⲛⲁ"/><!-- ⲛⲁ -->
<feat xlink:href="#orig_589" value="ϥ"/><!-- ϥ -->
<feat xlink:href="#orig_590" value="ⲛ"/><!-- ⲛ -->
<feat xlink:href="#orig_591" value="ⲟⲩ"/><!-- ⲟⲩ -->
<feat xlink:href="#orig_592" value="ⲏⲣⲡ"/><!-- ⲏⲣⲡ -->
<feat xlink:href="#orig_593" value="ⲉ"/><!-- ⲉ -->
<feat xlink:href="#orig_594" value="ϥ"/><!-- ϥ -->
<feat xlink:href="#orig_595" value="ⲙⲟϫⲧ"/><!-- ⲙⲟϫⲧ -->
<feat xlink:href="#orig_596" value="ϩⲓ"/><!-- ϩⲓ -->
<feat xlink:href="#orig_597" value="ϣⲁⲗ"/><!-- ϣⲁⲗ -->
<feat xlink:href="#orig_598" value="."/><!-- . -->
<feat xlink:href="#orig_599" value="ⲛⲧⲟϥ"/><!-- ⲛⲧⲟϥ -->
<feat xlink:href="#orig_600" value="ⲇⲉ"/><!-- ⲇⲉ -->
<feat xlink:href="#orig_601" value="ⲙⲡ"/><!-- ⲙⲡ -->
<feat xlink:href="#orig_602" value="ϥ"/><!-- ϥ -->
<feat xlink:href="#orig_603" value="ϫⲓⲧ"/><!-- ϫⲓⲧ -->
<feat xlink:href="#orig_604" value="ϥ"/><!-- ϥ -->
<feat xlink:href="#orig_605" value="ⲁ"/><!-- ⲁ -->
<feat xlink:href="#orig_606" value="ⲩ"/><!-- ⲩ -->
<feat xlink:href="#orig_607" value="ⲥⲧⲁⲩⲣⲟⲩ"/><!-- ⲥⲧⲁⲩⲣⲟⲩ -->
<feat xlink:href="#orig_608" value="ⲇⲉ"/><!-- ⲇⲉ -->
<feat xlink:href="#orig_609" value="ⲙⲙⲟ"/><!-- ⲙⲙⲟ -->
<feat xlink:href="#orig_610" value="ϥ"/><!-- ϥ -->
<feat xlink:href="#orig_611" value="."/><!-- . -->
<feat xlink:href="#orig_612" value="ⲁⲩⲱ"/><!-- ⲁⲩⲱ -->
<feat xlink:href="#orig_613" value="ⲁ"/><!-- ⲁ -->
<feat xlink:href="#orig_614" value="ⲩ"/><!-- ⲩ -->
<feat xlink:href="#orig_615" value="ⲡⲉϣ"/><!-- ⲡⲉϣ -->
<feat xlink:href="#orig_616" value="ⲛⲉϥ"/><!-- ⲛⲉϥ -->
<feat xlink:href="#orig_617" value="ϩⲟⲓⲧⲉ"/><!-- ϩⲟⲓⲧⲉ -->
<feat xlink:href="#orig_618" value="ⲉϩⲣⲁ"/><!-- ⲉϩⲣⲁ -->
<feat xlink:href="#orig_619" value="ⲩ"/><!-- ⲩ -->
<feat xlink:href="#orig_620" value="ⲁ"/><!-- ⲁ -->
<feat xlink:href="#orig_621" value="ⲩ"/><!-- ⲩ -->
<feat xlink:href="#orig_622" value="ⲛⲉϫ"/><!-- ⲛⲉϫ -->
<feat xlink:href="#orig_623" value="ⲕⲗⲏⲣⲟⲥ"/><!-- ⲕⲗⲏⲣⲟⲥ -->
<feat xlink:href="#orig_624" value="ⲉⲣⲟ"/><!-- ⲉⲣⲟ -->
<feat xlink:href="#orig_625" value="ⲟⲩ"/><!-- ⲟⲩ -->
<feat xlink:href="#orig_626" value="ϫⲉ"/><!-- ϫⲉ -->
<feat xlink:href="#orig_627" value="ⲛⲉⲣⲉ"/><!-- ⲛⲉⲣⲉ -->
<feat xlink:href="#orig_628" value="ⲡ"/><!-- ⲡ -->
<feat xlink:href="#orig_629" value="ⲟⲩⲁ"/><!-- ⲟⲩⲁ -->
<feat xlink:href="#orig_630" value="ⲡ"/><!-- ⲡ -->
<feat xlink:href="#orig_631" value="ⲟⲩⲁ"/><!-- ⲟⲩⲁ -->
<feat xlink:href="#orig_632" value="ⲛⲁ"/><!-- ⲛⲁ -->
<feat xlink:href="#orig_633" value="ϥⲓ"/><!-- ϥⲓ -->
<feat xlink:href="#orig_634" value="ⲟⲩ"/><!-- ⲟⲩ -->
<feat xlink:href="#orig_635" value="ⲛⲉ"/><!-- ⲛⲉ -->
<feat xlink:href="#orig_636" value="ⲡ"/><!-- ⲡ -->
<feat xlink:href="#orig_637" value="ⲛⲁⲩ"/><!-- ⲛⲁⲩ -->
<feat xlink:href="#orig_638" value="ⲇⲉ"/><!-- ⲇⲉ -->
<feat xlink:href="#orig_639" value="ⲡⲉ"/><!-- ⲡⲉ -->
<feat xlink:href="#orig_640" value="ⲛ"/><!-- ⲛ -->
<feat xlink:href="#orig_641" value="ϫⲡ"/><!-- ϫⲡ -->
<feat xlink:href="#orig_642" value="ϣⲟⲙⲧⲉ"/><!-- ϣⲟⲙⲧⲉ -->
<feat xlink:href="#orig_643" value="ⲁⲩⲱ"/><!-- ⲁⲩⲱ -->
<feat xlink:href="#orig_644" value="ⲁ"/><!-- ⲁ -->
<feat xlink:href="#orig_645" value="ⲩ"/><!-- ⲩ -->
<feat xlink:href="#orig_646" value="ⲥⲧⲁⲩⲣⲟⲩ"/><!-- ⲥⲧⲁⲩⲣⲟⲩ -->
<feat xlink:href="#orig_647" value="ⲙⲙⲟ"/><!-- ⲙⲙⲟ -->
<feat xlink:href="#orig_648" value="ϥ"/><!-- ϥ -->
<feat xlink:href="#orig_649" value="ⲛⲉⲣⲉ"/><!-- ⲛⲉⲣⲉ -->
<feat xlink:href="#orig_650" value="ⲧⲉϥ"/><!-- ⲧⲉϥ -->
<feat xlink:href="#orig_651" value="ⲁⲓⲧⲓⲁ"/><!-- ⲁⲓⲧⲓⲁ -->
<feat xlink:href="#orig_652" value="ⲇⲉ"/><!-- ⲇⲉ -->
<feat xlink:href="#orig_653" value="ⲥⲏϩ"/><!-- ⲥⲏϩ -->
<feat xlink:href="#orig_654" value="ϩⲓϫⲱ"/><!-- ϩⲓϫⲱ -->
<feat xlink:href="#orig_655" value="ϥ"/><!-- ϥ -->
<feat xlink:href="#orig_656" value="ϫⲉ"/><!-- ϫⲉ -->
<feat xlink:href="#orig_657" value="ⲡⲉ"/><!-- ⲡⲉ -->
<feat xlink:href="#orig_658" value="ⲣⲟ"/><!-- ⲣⲟ -->
<feat xlink:href="#orig_659" value="ⲛ"/><!-- ⲛ -->
<feat xlink:href="#orig_660" value="ⲓⲟⲩⲇⲁⲓ"/><!-- ⲓⲟⲩⲇⲁⲓ -->
<feat xlink:href="#orig_661" value="ⲁⲩⲱ"/><!-- ⲁⲩⲱ -->
<feat xlink:href="#orig_662" value="ⲁ"/><!-- ⲁ -->
<feat xlink:href="#orig_663" value="ⲩ"/><!-- ⲩ -->
<feat xlink:href="#orig_664" value="ⲥⲧⲁⲩⲣⲟⲩ"/><!-- ⲥⲧⲁⲩⲣⲟⲩ -->
<feat xlink:href="#orig_665" value="ⲛⲙⲙⲁ"/><!-- ⲛⲙⲙⲁ -->
<feat xlink:href="#orig_666" value="ϥ"/><!-- ϥ -->
<feat xlink:href="#orig_667" value="ⲛ"/><!-- ⲛ -->
<feat xlink:href="#orig_668" value="ⲥⲟⲟⲛⲉ"/><!-- ⲥⲟⲟⲛⲉ -->
<feat xlink:href="#orig_669" value="ⲥⲛⲁⲩ"/><!-- ⲥⲛⲁⲩ -->
<feat xlink:href="#orig_670" value="ⲟⲩⲁ"/><!-- ⲟⲩⲁ -->
<feat xlink:href="#orig_671" value="ⲛⲥⲁ"/><!-- ⲛⲥⲁ -->
<feat xlink:href="#orig_672" value="ⲟⲩⲛⲁⲙ"/><!-- ⲟⲩⲛⲁⲙ -->
<feat xlink:href="#orig_673" value="ⲁⲩⲱ"/><!-- ⲁⲩⲱ -->
<feat xlink:href="#orig_674" value="ⲟⲩⲁ"/><!-- ⲟⲩⲁ -->
<feat xlink:href="#orig_675" value="ⲛⲥⲁ"/><!-- ⲛⲥⲁ -->
<feat xlink:href="#orig_676" value="ϩⲃⲟⲩⲣ"/><!-- ϩⲃⲟⲩⲣ -->
<feat xlink:href="#orig_677" value="ⲙⲙⲟ"/><!-- ⲙⲙⲟ -->
<feat xlink:href="#orig_678" value="ϥ"/><!-- ϥ -->
<feat xlink:href="#orig_679" value="."/><!-- . -->
<feat xlink:href="#orig_680" value="["/><!-- [ -->
<feat xlink:href="#orig_681" value="--"/><!--  -  -->
<feat xlink:href="#orig_682" value="]"/><!-- ] -->
<feat xlink:href="#orig_683" value="ⲛ"/><!-- ⲛ -->
<feat xlink:href="#orig_684" value="ⲉⲧ"/><!-- ⲉⲧ -->
<feat xlink:href="#orig_685" value="ⲙⲟⲟϣⲉ"/><!-- ⲙⲟⲟϣⲉ -->
<feat xlink:href="#orig_686" value="ⲇⲉ"/><!-- ⲇⲉ -->
<feat xlink:href="#orig_687" value="ⲛⲉ"/><!-- ⲛⲉ -->
<feat xlink:href="#orig_688" value="ⲩ"/><!-- ⲩ -->
<feat xlink:href="#orig_689" value="ϫⲓⲟⲩⲁ"/><!-- ϫⲓ...ⲟⲩⲁ -->
<feat xlink:href="#orig_691" value="ⲉⲣⲟ"/><!-- ⲉⲣⲟ -->
<feat xlink:href="#orig_692" value="ϥ"/><!-- ϥ -->
<feat xlink:href="#orig_693" value="ⲉ"/><!-- ⲉ -->
<feat xlink:href="#orig_694" value="ⲩ"/><!-- ⲩ -->
<feat xlink:href="#orig_695" value="ⲕⲓⲙ"/><!-- ⲕⲓⲙ -->
<feat xlink:href="#orig_696" value="ⲛ"/><!-- ⲛ -->
<feat xlink:href="#orig_697" value="ⲛⲉⲩ"/><!-- ⲛⲉⲩ -->
<feat xlink:href="#orig_698" value="ⲁⲡⲏⲩⲉ"/><!-- ⲁⲡⲏⲩⲉ -->
<feat xlink:href="#orig_699" value="ⲛⲥⲱ"/><!-- ⲛⲥⲱ -->
<feat xlink:href="#orig_700" value="ϥ"/><!-- ϥ -->
<feat xlink:href="#orig_701" value="ⲉ"/><!-- ⲉ -->
<feat xlink:href="#orig_702" value="ⲩ"/><!-- ⲩ -->
<feat xlink:href="#orig_703" value="ϫⲱ"/><!-- ϫⲱ -->
<feat xlink:href="#orig_704" value="ⲙⲙⲟ"/><!-- ⲙⲙⲟ -->
<feat xlink:href="#orig_705" value="ⲥ"/><!-- ⲥ -->
<feat xlink:href="#orig_706" value="ϫⲉ"/><!-- ϫⲉ -->
<feat xlink:href="#orig_707" value="ⲟⲩⲁ"/><!-- ⲟⲩⲁ -->
<feat xlink:href="#orig_708" value="ⲡ"/><!-- ⲡ -->
<feat xlink:href="#orig_709" value="ⲉⲧ"/><!-- ⲉⲧ -->
<feat xlink:href="#orig_710" value="ⲛⲁ"/><!-- ⲛⲁ -->
<feat xlink:href="#orig_711" value="ⲃⲗ"/><!-- ⲃⲗ -->
<feat xlink:href="#orig_712" value="ⲡⲉ"/><!-- ⲡⲉ -->
<feat xlink:href="#orig_713" value="ⲣⲡⲉ"/><!-- ⲣⲡⲉ -->
<feat xlink:href="#orig_714" value="ⲉⲃⲟⲗ"/><!-- ⲉⲃⲟⲗ -->
<feat xlink:href="#orig_715" value="ⲛ"/><!-- ⲛ -->
<feat xlink:href="#orig_716" value="ϥ"/><!-- ϥ -->
<feat xlink:href="#orig_717" value="ⲕⲟⲧ"/><!-- ⲕⲟⲧ -->
<feat xlink:href="#orig_718" value="ϥ"/><!-- ϥ -->
<feat xlink:href="#orig_719" value="ⲛ"/><!-- ⲛ -->
<feat xlink:href="#orig_720" value="ϣⲟⲙⲛⲧ"/><!-- ϣⲟⲙⲛⲧ -->
<feat xlink:href="#orig_721" value="ⲛ"/><!-- ⲛ -->
<feat xlink:href="#orig_722" value="ϩⲟⲟⲩ"/><!-- ϩⲟⲟⲩ -->
<feat xlink:href="#orig_723" value="ⲁⲙⲟⲩ"/><!-- ⲁⲙⲟⲩ -->
<feat xlink:href="#orig_724" value="ⲉ"/><!-- ⲉ -->
<feat xlink:href="#orig_725" value="ⲡ"/><!-- ⲡ -->
<feat xlink:href="#orig_726" value="ⲉⲥⲏⲧ"/><!-- ⲉⲥⲏⲧ -->
<feat xlink:href="#orig_727" value="ϩⲓϫⲛ"/><!-- ϩⲓϫⲛ -->
<feat xlink:href="#orig_728" value="ⲡⲉ"/><!-- ⲡⲉ -->
<feat xlink:href="#orig_729" value="ⲥⲧⲁⲩⲣⲟⲥ"/><!-- ⲥⲧⲁⲩⲣⲟⲥ -->
<feat xlink:href="#orig_730" value="ⲛ"/><!-- ⲛ -->
<feat xlink:href="#orig_731" value="ⲅ"/><!-- ⲅ -->
<feat xlink:href="#orig_732" value="ⲛⲁϩⲙⲉ"/><!-- ⲛⲁϩⲙⲉ -->
<feat xlink:href="#orig_733" value="ⲕ"/><!-- ⲕ -->
<feat xlink:href="#orig_734" value="ϩⲓⲟⲙⲟⲓⲱⲥ"/><!-- ϩⲓⲟⲙⲟⲓⲱⲥ -->
<feat xlink:href="#orig_735" value="ⲛ"/><!-- ⲛ -->
<feat xlink:href="#orig_736" value="ⲕⲉ"/><!-- ⲕⲉ -->
<feat xlink:href="#orig_737" value="ⲁⲣⲭⲓⲉⲣⲉⲩⲥ"/><!-- ⲁⲣⲭⲓⲉⲣⲉⲩⲥ -->
<feat xlink:href="#orig_738" value="ⲛⲉ"/><!-- ⲛⲉ -->
<feat xlink:href="#orig_739" value="ⲩ"/><!-- ⲩ -->
<feat xlink:href="#orig_740" value="ⲥⲱⲃⲉ"/><!-- ⲥⲱⲃⲉ -->
<feat xlink:href="#orig_741" value="ⲛⲥⲱ"/><!-- ⲛⲥⲱ -->
<feat xlink:href="#orig_742" value="ϥ"/><!-- ϥ -->
<feat xlink:href="#orig_743" value="ⲙⲛ"/><!-- ⲙⲛ -->
<feat xlink:href="#orig_744" value="ⲛⲉ"/><!-- ⲛⲉ -->
<feat xlink:href="#orig_745" value="ⲅⲣⲁⲙⲙⲁⲧⲉⲩⲥ"/><!-- ⲅⲣⲁⲙⲙⲁⲧⲉⲩⲥ -->
<feat xlink:href="#orig_746" value="ⲉ"/><!-- ⲉ -->
<feat xlink:href="#orig_747" value="ⲩ"/><!-- ⲩ -->
<feat xlink:href="#orig_748" value="ϫⲱ"/><!-- ϫⲱ -->
<feat xlink:href="#orig_749" value="ⲙⲙⲟ"/><!-- ⲙⲙⲟ -->
<feat xlink:href="#orig_750" value="ⲥ"/><!-- ⲥ -->
<feat xlink:href="#orig_751" value="ⲛ"/><!-- ⲛ -->
<feat xlink:href="#orig_752" value="ⲛⲉⲩ"/><!-- ⲛⲉⲩ -->
<feat xlink:href="#orig_753" value="ⲉⲣⲏⲩ"/><!-- ⲉⲣⲏⲩ -->
<feat xlink:href="#orig_754" value="ϫⲉ"/><!-- ϫⲉ -->
<feat xlink:href="#orig_755" value="ϩⲉⲛ"/><!-- ϩⲉⲛ -->
<feat xlink:href="#orig_756" value="ⲕⲟⲟⲩⲉ"/><!-- ⲕⲟⲟⲩⲉ -->
<feat xlink:href="#orig_757" value="ⲛⲉ"/><!-- ⲛⲉ -->
<feat xlink:href="#orig_758" value="ⲛⲧ"/><!-- ⲛⲧ -->
<feat xlink:href="#orig_759" value="ⲁ"/><!-- ⲁ -->
<feat xlink:href="#orig_760" value="ϥ"/><!-- ϥ -->
<feat xlink:href="#orig_761" value="ⲛⲁϩⲙ"/><!-- ⲛⲁϩⲙ -->
<feat xlink:href="#orig_762" value="ⲟⲩ"/><!-- ⲟⲩ -->
<feat xlink:href="#orig_763" value="ⲛⲧⲟϥ"/><!-- ⲛⲧⲟϥ -->
<feat xlink:href="#orig_764" value="ⲇⲉ"/><!-- ⲇⲉ -->
<feat xlink:href="#orig_765" value="ⲛ"/><!-- ⲛ -->
<feat xlink:href="#orig_766" value="ϥ"/><!-- ϥ -->
<feat xlink:href="#orig_767" value="ⲛⲁ"/><!-- ⲛⲁ -->
<feat xlink:href="#orig_768" value="ϣ"/><!-- ϣ -->
<feat xlink:href="#orig_769" value="ⲛⲁϩⲙⲉ"/><!-- ⲛⲁϩⲙⲉ -->
<feat xlink:href="#orig_770" value="ϥ"/><!-- ϥ -->
<feat xlink:href="#orig_771" value="ⲁⲛ"/><!-- ⲁⲛ -->
<feat xlink:href="#orig_772" value="."/><!-- . -->
<feat xlink:href="#orig_773" value="ⲡⲉ"/><!-- ⲡⲉ -->
<feat xlink:href="#orig_774" value="ⲭⲣⲓⲥⲧⲟⲥ"/><!-- ⲭⲣⲓⲥⲧⲟⲥ -->
<feat xlink:href="#orig_775" value="ⲡⲉ"/><!-- ⲡⲉ -->
<feat xlink:href="#orig_776" value="ⲣⲟ"/><!-- ⲣⲟ -->
<feat xlink:href="#orig_777" value="ⲙ"/><!-- ⲙ -->
<feat xlink:href="#orig_778" value="ⲡ"/><!-- ⲡ -->
<feat xlink:href="#orig_779" value="ⲓⲥⲣⲁⲏⲗ"/><!-- ⲓⲥⲣⲁⲏⲗ -->
<feat xlink:href="#orig_780" value="ⲙⲁⲣⲉ"/><!-- ⲙⲁⲣⲉ -->
<feat xlink:href="#orig_781" value="ϥ"/><!-- ϥ -->
<feat xlink:href="#orig_782" value="ⲉⲓ"/><!-- ⲉⲓ -->
<feat xlink:href="#orig_783" value="ⲉ"/><!-- ⲉ -->
<feat xlink:href="#orig_784" value="ⲡ"/><!-- ⲡ -->
<feat xlink:href="#orig_785" value="ⲉⲥⲏⲧ"/><!-- ⲉⲥⲏⲧ -->
<feat xlink:href="#orig_786" value="ⲧⲉⲛⲟⲩ"/><!-- ⲧⲉⲛⲟⲩ -->
<feat xlink:href="#orig_787" value="ϩⲓϫⲛ"/><!-- ϩⲓϫⲛ -->
<feat xlink:href="#orig_788" value="ⲡⲉ"/><!-- ⲡⲉ -->
<feat xlink:href="#orig_789" value="ⲥⲧⲁⲩⲣⲟⲥ"/><!-- ⲥⲧⲁⲩⲣⲟⲥ -->
<feat xlink:href="#orig_790" value="ϫⲉ"/><!-- ϫⲉ -->
<feat xlink:href="#orig_791" value="ⲉⲛⲉ"/><!-- ⲉⲛⲉ -->
<feat xlink:href="#orig_792" value="ⲛⲁⲩ"/><!-- ⲛⲁⲩ -->
<feat xlink:href="#orig_793" value="ⲛ"/><!-- ⲛ -->
<feat xlink:href="#orig_794" value="ⲧⲛ"/><!-- ⲧⲛ -->
<feat xlink:href="#orig_795" value="ⲡⲓⲥⲧⲉⲩⲉ"/><!-- ⲡⲓⲥⲧⲉⲩⲉ -->
<feat xlink:href="#orig_796" value="ⲉⲣⲟ"/><!-- ⲉⲣⲟ -->
<feat xlink:href="#orig_797" value="ϥ"/><!-- ϥ -->
<feat xlink:href="#orig_798" value="."/><!-- . -->
<feat xlink:href="#orig_799" value="ⲁⲩⲱ"/><!-- ⲁⲩⲱ -->
<feat xlink:href="#orig_800" value="ⲛ"/><!-- ⲛ -->
<feat xlink:href="#orig_801" value="ⲕⲉ"/><!-- ⲕⲉ -->
<feat xlink:href="#orig_802" value="ⲥⲟⲟⲛⲉ"/><!-- ⲥⲟⲟⲛⲉ -->
<feat xlink:href="#orig_803" value="ⲛⲧ"/><!-- ⲛⲧ -->
<feat xlink:href="#orig_804" value="ⲁ"/><!-- ⲁ -->
<feat xlink:href="#orig_805" value="ⲩ"/><!-- ⲩ -->
<feat xlink:href="#orig_806" value="ⲥⲧⲁⲩⲣⲟⲩ"/><!-- ⲥⲧⲁⲩⲣⲟⲩ -->
<feat xlink:href="#orig_807" value="ⲙⲙⲟ"/><!-- ⲙⲙⲟ -->
<feat xlink:href="#orig_808" value="ⲟⲩ"/><!-- ⲟⲩ -->
<feat xlink:href="#orig_809" value="ⲛⲙⲙⲁ"/><!-- ⲛⲙⲙⲁ -->
<feat xlink:href="#orig_810" value="ϥ"/><!-- ϥ -->
<feat xlink:href="#orig_811" value="ⲁ"/><!-- ⲁ -->
<feat xlink:href="#orig_812" value="ⲩ"/><!-- ⲩ -->
<feat xlink:href="#orig_813" value="ⲛⲉϭⲛⲟⲩϭ"/><!-- ⲛⲉϭⲛⲟⲩϭ -->
<feat xlink:href="#orig_814" value="ϥ"/><!-- ϥ -->
<feat xlink:href="#orig_815" value="."/><!-- . -->
<feat xlink:href="#orig_816" value="ⲛⲧⲉⲣⲉ"/><!-- ⲛⲧⲉⲣⲉ -->
<feat xlink:href="#orig_817" value="ⲡ"/><!-- ⲡ -->
<feat xlink:href="#orig_818" value="ⲛⲁⲩ"/><!-- ⲛⲁⲩ -->
<feat xlink:href="#orig_819" value="ⲇⲉ"/><!-- ⲇⲉ -->
<feat xlink:href="#orig_820" value="ⲛ"/><!-- ⲛ -->
<feat xlink:href="#orig_821" value="ϫⲡ"/><!-- ϫⲡ -->
<feat xlink:href="#orig_822" value="ⲥⲟ"/><!-- ⲥⲟ -->
<feat xlink:href="#orig_823" value="ϣⲱⲡⲉ"/><!-- ϣⲱⲡⲉ -->
<feat xlink:href="#orig_824" value="ⲁ"/><!-- ⲁ -->
<feat xlink:href="#orig_825" value="ⲩ"/><!-- ⲩ -->
<feat xlink:href="#orig_826" value="ⲕⲁⲕⲉ"/><!-- ⲕⲁⲕⲉ -->
<feat xlink:href="#orig_827" value="ϣⲱⲡⲉ"/><!-- ϣⲱⲡⲉ -->
<feat xlink:href="#orig_828" value="ϩⲓϫⲛ"/><!-- ϩⲓϫⲛ -->
<feat xlink:href="#orig_829" value="ⲡ"/><!-- ⲡ -->
<feat xlink:href="#orig_830" value="ⲕⲁϩ"/><!-- ⲕⲁϩ -->
<feat xlink:href="#orig_831" value="ⲧⲏⲣ"/><!-- ⲧⲏⲣ -->
<feat xlink:href="#orig_832" value="ϥ"/><!-- ϥ -->
<feat xlink:href="#orig_833" value="ϣⲁ"/><!-- ϣⲁ -->
<feat xlink:href="#orig_834" value="ⲡ"/><!-- ⲡ -->
<feat xlink:href="#orig_835" value="ⲛⲁⲩ"/><!-- ⲛⲁⲩ -->
<feat xlink:href="#orig_836" value="ⲛ"/><!-- ⲛ -->
<feat xlink:href="#orig_837" value="ϫⲡ"/><!-- ϫⲡ -->
<feat xlink:href="#orig_838" value="ⲥⲓⲧⲉ"/><!-- ⲥⲓⲧⲉ -->
<feat xlink:href="#orig_839" value="."/><!-- . -->
<feat xlink:href="#orig_840" value="ⲁⲩⲱ"/><!-- ⲁⲩⲱ -->
<feat xlink:href="#orig_841" value="ⲙ"/><!-- ⲙ -->
<feat xlink:href="#orig_842" value="ⲡ"/><!-- ⲡ -->
<feat xlink:href="#orig_843" value="ⲛⲁⲩ"/><!-- ⲛⲁⲩ -->
<feat xlink:href="#orig_844" value="ⲛ"/><!-- ⲛ -->
<feat xlink:href="#orig_845" value="ϫⲡ"/><!-- ϫⲡ -->
<feat xlink:href="#orig_846" value="ⲯⲓⲧⲉ"/><!-- ⲯⲓⲧⲉ -->
<feat xlink:href="#orig_847" value="ⲁ"/><!-- ⲁ -->
<feat xlink:href="#orig_848" value="ϥ"/><!-- ϥ -->
<feat xlink:href="#orig_849" value="ⲱϣ"/><!-- ⲱϣ -->
<feat xlink:href="#orig_850" value="ⲉⲃⲟⲗ"/><!-- ⲉⲃⲟⲗ -->
<feat xlink:href="#orig_851" value="ⲛϭⲓ"/><!-- ⲛϭⲓ -->
<feat xlink:href="#orig_852" value="ⲓⲏⲥⲟⲩⲥ"/><!-- ⲓⲏⲥⲟⲩⲥ -->
<feat xlink:href="#orig_853" value="ϩⲛ"/><!-- ϩⲛ -->
<feat xlink:href="#orig_854" value="ⲟⲩ"/><!-- ⲟⲩ -->
<feat xlink:href="#orig_855" value="ⲛⲟϭ"/><!-- ⲛⲟϭ -->
<feat xlink:href="#orig_856" value="ⲛ"/><!-- ⲛ -->
<feat xlink:href="#orig_857" value="ϩⲣⲟⲟⲩ"/><!-- ϩⲣⲟⲟⲩ -->
<feat xlink:href="#orig_858" value="ϫⲉ"/><!-- ϫⲉ -->
<feat xlink:href="#orig_859" value="ⲉⲗⲱⲉⲓ"/><!-- ⲉⲗⲱⲉⲓ -->
<feat xlink:href="#orig_860" value="ⲉⲗⲱⲉⲓ"/><!-- ⲉⲗⲱⲉⲓ -->
<feat xlink:href="#orig_861" value="ⲗⲁⲙⲁ"/><!-- ⲗⲁⲙⲁ -->
<feat xlink:href="#orig_862" value="ⲥⲁⲭⲑⲁⲛⲉⲓ"/><!-- ⲥⲁⲭⲑⲁⲛⲉⲓ -->
<feat xlink:href="#orig_863" value="."/><!-- . -->
<feat xlink:href="#orig_864" value="ⲉⲧⲉ"/><!-- ⲉⲧⲉ -->
<feat xlink:href="#orig_865" value="ⲡⲁⲓ"/><!-- ⲡⲁⲓ -->
<feat xlink:href="#orig_866" value="ⲡⲉ"/><!-- ⲡⲉ -->
<feat xlink:href="#orig_867" value="ϣⲁ"/><!-- ϣⲁ -->
<feat xlink:href="#orig_868" value="ⲩ"/><!-- ⲩ -->
<feat xlink:href="#orig_869" value="ϩⲉⲣⲙⲉⲛⲉⲩⲉ"/><!-- ϩⲉⲣⲙⲉⲛⲉⲩⲉ -->
<feat xlink:href="#orig_870" value="ⲙⲙⲟ"/><!-- ⲙⲙⲟ -->
<feat xlink:href="#orig_871" value="ϥ"/><!-- ϥ -->
<feat xlink:href="#orig_872" value="ϫⲉ"/><!-- ϫⲉ -->
<feat xlink:href="#orig_873" value="ⲡⲁ"/><!-- ⲡⲁ -->
<feat xlink:href="#orig_874" value="ⲛⲟⲩⲧⲉ"/><!-- ⲛⲟⲩⲧⲉ -->
<feat xlink:href="#orig_875" value="ⲡⲁ"/><!-- ⲡⲁ -->
<feat xlink:href="#orig_876" value="ⲛⲟⲩⲧⲉ"/><!-- ⲛⲟⲩⲧⲉ -->
<feat xlink:href="#orig_877" value="ⲉⲧⲃⲉ"/><!-- ⲉⲧⲃⲉ -->
<feat xlink:href="#orig_878" value="ⲟⲩ"/><!-- ⲟⲩ -->
<feat xlink:href="#orig_879" value="ⲁ"/><!-- ⲁ -->
<feat xlink:href="#orig_880" value="ⲕ"/><!-- ⲕ -->
<feat xlink:href="#orig_881" value="ⲕⲁⲁⲧ"/><!-- ⲕⲁⲁⲧ -->
<feat xlink:href="#orig_882" value="ⲛⲥⲱ"/><!-- ⲛⲥⲱ -->
<feat xlink:href="#orig_883" value="ⲕ"/><!-- ⲕ -->
<feat xlink:href="#orig_884" value="."/><!-- . -->
<feat xlink:href="#orig_885" value="ⲁⲩⲱ"/><!-- ⲁⲩⲱ -->
<feat xlink:href="#orig_886" value="ϩⲟⲓⲛⲉ"/><!-- ϩⲟⲓⲛⲉ -->
<feat xlink:href="#orig_887" value="ⲛ"/><!-- ⲛ -->
<feat xlink:href="#orig_888" value="ⲛ"/><!-- ⲛ -->
<feat xlink:href="#orig_889" value="ⲉⲧ"/><!-- ⲉⲧ -->
<feat xlink:href="#orig_890" value="ⲁϩⲉ"/><!-- ⲁϩⲉ -->
<feat xlink:href="#orig_891" value="ⲣⲁⲧ"/><!-- ⲣⲁⲧ -->
<feat xlink:href="#orig_892" value="ⲟⲩ"/><!-- ⲟⲩ -->
<feat xlink:href="#orig_893" value="ⲙ"/><!-- ⲙ -->
<feat xlink:href="#orig_894" value="ⲡ"/><!-- ⲡ -->
<feat xlink:href="#orig_895" value="ⲙⲁ"/><!-- ⲙⲁ -->
<feat xlink:href="#orig_896" value="ⲉⲧ"/><!-- ⲉⲧ -->
<feat xlink:href="#orig_897" value="ⲙⲙⲁⲩ"/><!-- ⲙⲙⲁⲩ -->
<feat xlink:href="#orig_898" value="ⲛⲧⲉⲣ"/><!-- ⲛⲧⲉⲣ -->
<feat xlink:href="#orig_899" value="ⲟⲩ"/><!-- ⲟⲩ -->
<feat xlink:href="#orig_900" value="ⲥⲱⲧⲙ"/><!-- ⲥⲱⲧⲙ -->
<feat xlink:href="#orig_901" value="ⲡⲉϫⲁ"/><!-- ⲡⲉϫⲁ -->
<feat xlink:href="#orig_902" value="ⲩ"/><!-- ⲩ -->
<feat xlink:href="#orig_903" value="ϫⲉ"/><!-- ϫⲉ -->
<feat xlink:href="#orig_904" value="ⲉⲓⲥ"/><!-- ⲉⲓⲥ -->
<feat xlink:href="#orig_905" value="ϩⲏⲏⲧⲉ"/><!-- ϩⲏⲏⲧⲉ -->
<feat xlink:href="#orig_906" value="ϥ"/><!-- ϥ -->
<feat xlink:href="#orig_907" value="ⲙⲟⲩⲧⲉ"/><!-- ⲙⲟⲩⲧⲉ -->
<feat xlink:href="#orig_908" value="ⲉ"/><!-- ⲉ -->
<feat xlink:href="#orig_909" value="ϩⲏⲗⲉⲓⲁⲥ"/><!-- ϩⲏⲗⲉⲓⲁⲥ -->
<feat xlink:href="#orig_910" value="."/><!-- . -->
<feat xlink:href="#orig_911" value="ⲁ"/><!-- ⲁ -->
<feat xlink:href="#orig_912" value="ⲟⲩⲁ"/><!-- ⲟⲩⲁ -->
<feat xlink:href="#orig_913" value="ⲇⲉ"/><!-- ⲇⲉ -->
<feat xlink:href="#orig_914" value="ⲡⲱⲧ"/><!-- ⲡⲱⲧ -->
<feat xlink:href="#orig_915" value="ⲁ"/><!-- ⲁ -->
<feat xlink:href="#orig_916" value="ϥ"/><!-- ϥ -->
<feat xlink:href="#orig_917" value="ⲙⲁϩ"/><!-- ⲙⲁϩ -->
<feat xlink:href="#orig_918" value="ⲟⲩ"/><!-- ⲟⲩ -->
<feat xlink:href="#orig_919" value="ⲥⲡⲟⲅⲅⲟⲥ"/><!-- ⲥⲡⲟⲅⲅⲟⲥ -->
<feat xlink:href="#orig_920" value="ⲛ"/><!-- ⲛ -->
<feat xlink:href="#orig_921" value="ϩⲙϫ"/><!-- ϩⲙϫ -->
<feat xlink:href="#orig_922" value="ⲁ"/><!-- ⲁ -->
<feat xlink:href="#orig_923" value="ϥ"/><!-- ϥ -->
<feat xlink:href="#orig_924" value="ⲕⲁⲁ"/><!-- ⲕⲁⲁ -->
<feat xlink:href="#orig_925" value="ⲥ"/><!-- ⲥ -->
<feat xlink:href="#orig_926" value="ϩⲓϫⲛ"/><!-- ϩⲓϫⲛ -->
<feat xlink:href="#orig_927" value="ⲟⲩ"/><!-- ⲟⲩ -->
<feat xlink:href="#orig_928" value="ⲕⲁϣ"/><!-- ⲕⲁϣ -->
<feat xlink:href="#orig_929" value="ⲁ"/><!-- ⲁ -->
<feat xlink:href="#orig_930" value="ϥ"/><!-- ϥ -->
<feat xlink:href="#orig_931" value="ⲧⲥⲟ"/><!-- ⲧⲥⲟ -->
<feat xlink:href="#orig_932" value="ϥ"/><!-- ϥ -->
<feat xlink:href="#orig_933" value="ⲉ"/><!-- ⲉ -->
<feat xlink:href="#orig_934" value="ϥ"/><!-- ϥ -->
<feat xlink:href="#orig_935" value="ϫⲱ"/><!-- ϫⲱ -->
<feat xlink:href="#orig_936" value="ⲙⲙⲟ"/><!-- ⲙⲙⲟ -->
<feat xlink:href="#orig_937" value="ⲥ"/><!-- ⲥ -->
<feat xlink:href="#orig_938" value="ϫⲉ"/><!-- ϫⲉ -->
<feat xlink:href="#orig_939" value="ϭⲱ"/><!-- ϭⲱ -->
<feat xlink:href="#orig_940" value="ⲛ"/><!-- ⲛ -->
<feat xlink:href="#orig_941" value="ⲧⲛ"/><!-- ⲧⲛ -->
<feat xlink:href="#orig_942" value="ⲛⲁⲩ"/><!-- ⲛⲁⲩ -->
<feat xlink:href="#orig_943" value="ϫⲉ"/><!-- ϫⲉ -->
<feat xlink:href="#orig_944" value="ϩⲏⲗⲉⲓⲁⲥ"/><!-- ϩⲏⲗⲉⲓⲁⲥ -->
<feat xlink:href="#orig_945" value="ⲛⲁ"/><!-- ⲛⲁ -->
<feat xlink:href="#orig_946" value="ⲉⲓ"/><!-- ⲉⲓ -->
<feat xlink:href="#orig_947" value="ⲉ"/><!-- ⲉ -->
<feat xlink:href="#orig_948" value="ⲛⲧ"/><!-- ⲛⲧ -->
<feat xlink:href="#orig_949" value="ϥ"/><!-- ϥ -->
<feat xlink:href="#orig_950" value="ⲉ"/><!-- ⲉ -->
<feat xlink:href="#orig_951" value="ⲡⲉ"/><!-- ⲡⲉ -->
<feat xlink:href="#orig_952" value="ⲥⲏⲧ"/><!-- ⲥⲏⲧ -->
<feat xlink:href="#orig_953" value="."/><!-- . -->
<feat xlink:href="#orig_954" value="ⲓⲏⲥⲟⲩⲥ"/><!-- ⲓⲏⲥⲟⲩⲥ -->
<feat xlink:href="#orig_955" value="ⲇⲉ"/><!-- ⲇⲉ -->
<feat xlink:href="#orig_956" value="ⲛⲧⲉⲣⲉ"/><!-- ⲛⲧⲉⲣⲉ -->
<feat xlink:href="#orig_957" value="ϥ"/><!-- ϥ -->
<feat xlink:href="#orig_958" value="ⲛⲟⲩϫ"/><!-- ⲛⲟⲩϫ -->
<feat xlink:href="#orig_959" value="ⲟⲩ"/><!-- ⲟⲩ -->
<feat xlink:href="#orig_960" value="ⲛⲟϭ"/><!-- ⲛⲟϭ -->
<feat xlink:href="#orig_961" value="ⲛ"/><!-- ⲛ -->
<feat xlink:href="#orig_962" value="ϩⲣⲟⲟⲩ"/><!-- ϩⲣⲟⲟⲩ -->
<feat xlink:href="#orig_963" value="ⲁ"/><!-- ⲁ -->
<feat xlink:href="#orig_964" value="ϥ"/><!-- ϥ -->
<feat xlink:href="#orig_965" value="ϯ"/><!-- ϯ -->
<feat xlink:href="#orig_966" value="ⲡⲉ"/><!-- ⲡⲉ -->
<feat xlink:href="#orig_967" value="ⲡⲛⲉⲩⲙⲁ"/><!-- ⲡⲛⲉⲩⲙⲁ -->
<feat xlink:href="#orig_968" value="ⲁⲩⲱ"/><!-- ⲁⲩⲱ -->
<feat xlink:href="#orig_969" value="ⲡ"/><!-- ⲡ -->
<feat xlink:href="#orig_970" value="ⲕⲁⲧⲁⲡⲉⲧⲁⲥⲙⲁ"/><!-- ⲕⲁⲧⲁⲡⲉⲧⲁⲥⲙⲁ -->
<feat xlink:href="#orig_971" value="ⲙ"/><!-- ⲙ -->
<feat xlink:href="#orig_972" value="ⲡⲉ"/><!-- ⲡⲉ -->
<feat xlink:href="#orig_973" value="ⲣⲡⲉ"/><!-- ⲣⲡⲉ -->
<feat xlink:href="#orig_974" value="ⲁ"/><!-- ⲁ -->
<feat xlink:href="#orig_975" value="ϥ"/><!-- ϥ -->
<feat xlink:href="#orig_976" value="ⲡⲱϩ"/><!-- ⲡⲱϩ -->
<feat xlink:href="#orig_977" value="ⲁ"/><!-- ⲁ -->
<feat xlink:href="#orig_978" value="ϥ"/><!-- ϥ -->
<feat xlink:href="#orig_979" value="ⲣⲥⲛⲁⲩ"/><!-- ⲣ...ⲥⲛⲁⲩ -->
<feat xlink:href="#orig_981" value="ϫⲓⲛ"/><!-- ϫⲓⲛ -->
<feat xlink:href="#orig_982" value="ⲧ"/><!-- ⲧ -->
<feat xlink:href="#orig_983" value="ⲡⲉ"/><!-- ⲡⲉ -->
<feat xlink:href="#orig_984" value="ⲉ"/><!-- ⲉ -->
<feat xlink:href="#orig_985" value="ⲡⲉ"/><!-- ⲡⲉ -->
<feat xlink:href="#orig_986" value="ⲥⲏⲧ"/><!-- ⲥⲏⲧ -->
<feat xlink:href="#orig_987" value="ⲛⲧⲉⲣⲉ"/><!-- ⲛⲧⲉⲣⲉ -->
<feat xlink:href="#orig_988" value="ϥ"/><!-- ϥ -->
<feat xlink:href="#orig_989" value="ⲛⲁⲩ"/><!-- ⲛⲁⲩ -->
<feat xlink:href="#orig_990" value="ⲇⲉ"/><!-- ⲇⲉ -->
<feat xlink:href="#orig_991" value="ⲛϭⲓ"/><!-- ⲛϭⲓ -->
<feat xlink:href="#orig_992" value="ⲡ"/><!-- ⲡ -->
<feat xlink:href="#orig_993" value="ⲕⲉⲛⲧⲩⲣⲓⲱⲛ"/><!-- ⲕⲉⲛⲧⲩⲣⲓⲱⲛ -->
<feat xlink:href="#orig_994" value="ⲡ"/><!-- ⲡ -->
<feat xlink:href="#orig_995" value="ⲉⲧ"/><!-- ⲉⲧ -->
<feat xlink:href="#orig_996" value="ⲁϩⲉ"/><!-- ⲁϩⲉ -->
<feat xlink:href="#orig_997" value="ⲣⲁⲧ"/><!-- ⲣⲁⲧ -->
<feat xlink:href="#orig_998" value="ϥ"/><!-- ϥ -->
<feat xlink:href="#orig_999" value="ⲙ"/><!-- ⲙ -->
<feat xlink:href="#orig_1000" value="ⲡⲉϥ"/><!-- ⲡⲉϥ -->
<feat xlink:href="#orig_1001" value="ⲙⲧⲟ"/><!-- ⲙⲧⲟ -->
<feat xlink:href="#orig_1002" value="ⲉⲃⲟⲗ"/><!-- ⲉⲃⲟⲗ -->
<feat xlink:href="#orig_1003" value="ϫⲉ"/><!-- ϫⲉ -->
<feat xlink:href="#orig_1004" value="ⲁ"/><!-- ⲁ -->
<feat xlink:href="#orig_1005" value="ϥ"/><!-- ϥ -->
<feat xlink:href="#orig_1006" value="ⲕⲁ"/><!-- ⲕⲁ -->
<feat xlink:href="#orig_1007" value="ⲡⲉ"/><!-- ⲡⲉ -->
<feat xlink:href="#orig_1008" value="ⲧⲏⲩ"/><!-- ⲧⲏⲩ -->
<feat xlink:href="#orig_1009" value="ⲓⲛⲁⲓ"/><!-- ⲓⲛⲁⲓ -->
<feat xlink:href="#orig_1010" value="."/><!-- . -->
<feat xlink:href="#orig_1011" value="ⲡⲉϫⲁ"/><!-- ⲡⲉϫⲁ -->
<feat xlink:href="#orig_1012" value="ϥ"/><!-- ϥ -->
<feat xlink:href="#orig_1013" value="ϫⲉ"/><!-- ϫⲉ -->
<feat xlink:href="#orig_1014" value="ⲁⲗⲏⲑⲱⲥ"/><!-- ⲁⲗⲏⲑⲱⲥ -->
<feat xlink:href="#orig_1015" value="ⲡⲉⲓ"/><!-- ⲡⲉⲓ -->
<feat xlink:href="#orig_1016" value="ⲣⲱⲙⲉ"/><!-- ⲣⲱⲙⲉ -->
<feat xlink:href="#orig_1017" value="ⲟⲩ"/><!-- ⲟⲩ -->
<feat xlink:href="#orig_1018" value="ϣⲏⲣⲉ"/><!-- ϣⲏⲣⲉ -->
<feat xlink:href="#orig_1019" value="ⲡⲉ"/><!-- ⲡⲉ -->
<feat xlink:href="#orig_1020" value="ⲛ"/><!-- ⲛ -->
<feat xlink:href="#orig_1021" value="ⲛⲟⲩⲧⲉ"/><!-- ⲛⲟⲩⲧⲉ -->
<feat xlink:href="#orig_1022" value="ⲛⲉ"/><!-- ⲛⲉ -->
<feat xlink:href="#orig_1023" value="ⲩⲛ"/><!-- ⲩⲛ -->
<feat xlink:href="#orig_1024" value="ϩⲉⲛ"/><!-- ϩⲉⲛ -->
<feat xlink:href="#orig_1025" value="ϩⲓⲟⲙⲉ"/><!-- ϩⲓⲟⲙⲉ -->
<feat xlink:href="#orig_1026" value="ⲇⲉ"/><!-- ⲇⲉ -->
<feat xlink:href="#orig_1027" value="ⲁϩⲉ"/><!-- ⲁϩⲉ -->
<feat xlink:href="#orig_1028" value="ⲣⲁⲧ"/><!-- ⲣⲁⲧ -->
<feat xlink:href="#orig_1029" value="ⲟⲩ"/><!-- ⲟⲩ -->
<feat xlink:href="#orig_1030" value="ⲙ"/><!-- ⲙ -->
<feat xlink:href="#orig_1031" value="ⲡ"/><!-- ⲡ -->
<feat xlink:href="#orig_1032" value="ⲟⲩⲉ"/><!-- ⲟⲩⲉ -->
<feat xlink:href="#orig_1033" value="ⲉ"/><!-- ⲉ -->
<feat xlink:href="#orig_1034" value="ⲩ"/><!-- ⲩ -->
<feat xlink:href="#orig_1035" value="ϭⲱϣⲧ"/><!-- ϭⲱϣⲧ -->
<feat xlink:href="#orig_1036" value="ⲉ"/><!-- ⲉ -->
<feat xlink:href="#orig_1037" value="ⲥ"/><!-- ⲥ -->
<feat xlink:href="#orig_1038" value="ⲛϩⲏⲧ"/><!-- ⲛϩⲏⲧ -->
<feat xlink:href="#orig_1039" value="ⲟⲩ"/><!-- ⲟⲩ -->
<feat xlink:href="#orig_1040" value="ⲛϭⲓ"/><!-- ⲛϭⲓ -->
<feat xlink:href="#orig_1041" value="ⲙⲁⲣⲓⲁ"/><!-- ⲙⲁⲣⲓⲁ -->
<feat xlink:href="#orig_1042" value="ⲧ"/><!-- ⲧ -->
<feat xlink:href="#orig_1043" value="ⲙⲁⲅⲇⲁⲗⲏⲛⲏ"/><!-- ⲙⲁⲅⲇⲁⲗⲏⲛⲏ -->
<feat xlink:href="#orig_1044" value="ⲁⲩⲱ"/><!-- ⲁⲩⲱ -->
<feat xlink:href="#orig_1045" value="ⲙⲁⲣⲓⲁ"/><!-- ⲙⲁⲣⲓⲁ -->
<feat xlink:href="#orig_1046" value="ⲧⲁ"/><!-- ⲧⲁ -->
<feat xlink:href="#orig_1047" value="ⲡ"/><!-- ⲡ -->
<feat xlink:href="#orig_1048" value="ⲕⲟⲩⲉⲓ"/><!-- ⲕⲟⲩⲉⲓ -->
<feat xlink:href="#orig_1049" value="ⲛ"/><!-- ⲛ -->
<feat xlink:href="#orig_1050" value="ⲓⲁⲕⲱⲃⲟⲥ"/><!-- ⲓⲁⲕⲱⲃⲟⲥ -->
<feat xlink:href="#orig_1051" value="."/><!-- . -->
<feat xlink:href="#orig_1052" value="ⲁⲩⲱ"/><!-- ⲁⲩⲱ -->
<feat xlink:href="#orig_1053" value="ⲧ"/><!-- ⲧ -->
<feat xlink:href="#orig_1054" value="ⲙⲁⲁⲩ"/><!-- ⲙⲁⲁⲩ -->
<feat xlink:href="#orig_1055" value="ⲛ"/><!-- ⲛ -->
<feat xlink:href="#orig_1056" value="ⲓⲱⲥⲏ"/><!-- ⲓⲱⲥⲏ -->
<feat xlink:href="#orig_1057" value="ⲙⲛ"/><!-- ⲙⲛ -->
<feat xlink:href="#orig_1058" value="ⲥⲁⲗⲱⲙⲏ"/><!-- ⲥⲁⲗⲱⲙⲏ -->
<feat xlink:href="#orig_1059" value="."/><!-- . -->
<feat xlink:href="#orig_1060" value="ⲛⲁⲓ"/><!-- ⲛⲁⲓ -->
<feat xlink:href="#orig_1061" value="ⲛⲧ"/><!-- ⲛⲧ -->
<feat xlink:href="#orig_1062" value="ⲁ"/><!-- ⲁ -->
<feat xlink:href="#orig_1063" value="ⲩ"/><!-- ⲩ -->
<feat xlink:href="#orig_1064" value="ⲁϩⲟⲩ"/><!-- ⲁϩⲟⲩ -->
<feat xlink:href="#orig_1065" value="ⲛⲥⲱ"/><!-- ⲛⲥⲱ -->
<feat xlink:href="#orig_1066" value="ϥ"/><!-- ϥ -->
<feat xlink:href="#orig_1067" value="ϫⲓⲛ"/><!-- ϫⲓⲛ -->
<feat xlink:href="#orig_1068" value="ⲧ"/><!-- ⲧ -->
<feat xlink:href="#orig_1069" value="ⲅⲁⲗⲓⲗⲁⲓⲁ"/><!-- ⲅⲁⲗⲓⲗⲁⲓⲁ -->
<feat xlink:href="#orig_1070" value="ⲉ"/><!-- ⲉ -->
<feat xlink:href="#orig_1071" value="ⲩ"/><!-- ⲩ -->
<feat xlink:href="#orig_1072" value="ⲇⲓⲁⲕⲟⲛⲓ"/><!-- ⲇⲓⲁⲕⲟⲛⲓ -->
<feat xlink:href="#orig_1073" value="ⲛⲁ"/><!-- ⲛⲁ -->
<feat xlink:href="#orig_1074" value="ϥ"/><!-- ϥ -->
<feat xlink:href="#orig_1075" value="ⲁⲩⲱ"/><!-- ⲁⲩⲱ -->
<feat xlink:href="#orig_1076" value="ϩⲉⲛ"/><!-- ϩⲉⲛ -->
<feat xlink:href="#orig_1077" value="ⲕⲉ"/><!-- ⲕⲉ -->
<feat xlink:href="#orig_1078" value="ϩⲓⲟⲙⲉ"/><!-- ϩⲓⲟⲙⲉ -->
<feat xlink:href="#orig_1079" value="ⲧⲏⲣ"/><!-- ⲧⲏⲣ -->
<feat xlink:href="#orig_1080" value="ⲟⲩ"/><!-- ⲟⲩ -->
<feat xlink:href="#orig_1081" value="ⲉ"/><!-- ⲉ -->
<feat xlink:href="#orig_1082" value="ⲁ"/><!-- ⲁ -->
<feat xlink:href="#orig_1083" value="ⲩ"/><!-- ⲩ -->
<feat xlink:href="#orig_1084" value="ⲉⲓ"/><!-- ⲉⲓ -->
<feat xlink:href="#orig_1085" value="ⲛⲙⲙⲁ"/><!-- ⲛⲙⲙⲁ -->
<feat xlink:href="#orig_1086" value="ϥ"/><!-- ϥ -->
<feat xlink:href="#orig_1087" value="ⲉϩⲣⲁⲓ"/><!-- ⲉϩⲣⲁⲓ -->
<feat xlink:href="#orig_1088" value="ⲉ"/><!-- ⲉ -->
<feat xlink:href="#orig_1089" value="ⲧ"/><!-- ⲧ -->
<feat xlink:href="#orig_1090" value="ϩⲓⲉⲣⲟⲥⲟⲗⲩⲙⲁ"/><!-- ϩⲓⲉⲣⲟⲥⲟⲗⲩⲙⲁ -->
<feat xlink:href="#orig_1091" value="."/><!-- . -->
<feat xlink:href="#orig_1092" value="ⲁⲩⲱ"/><!-- ⲁⲩⲱ -->
<feat xlink:href="#orig_1093" value="ⲛⲧⲉⲣⲉ"/><!-- ⲛⲧⲉⲣⲉ -->
<feat xlink:href="#orig_1094" value="ⲣⲟⲩϩⲉ"/><!-- ⲣⲟⲩϩⲉ -->
<feat xlink:href="#orig_1095" value="ϣⲱⲡⲉ"/><!-- ϣⲱⲡⲉ -->
<feat xlink:href="#orig_1096" value="ⲉⲃⲟⲗ"/><!-- ⲉⲃⲟⲗ -->
<feat xlink:href="#orig_1097" value="ϫⲉ"/><!-- ϫⲉ -->
<feat xlink:href="#orig_1098" value="ⲧ"/><!-- ⲧ -->
<feat xlink:href="#orig_1099" value="ⲡⲁⲣⲁⲥⲕⲉⲩⲏ"/><!-- ⲡⲁⲣⲁⲥⲕⲉⲩⲏ -->
<feat xlink:href="#orig_1100" value="ⲧⲉ"/><!-- ⲧⲉ -->
<feat xlink:href="#orig_1101" value="ⲉⲧⲉ"/><!-- ⲉⲧⲉ -->
<feat xlink:href="#orig_1102" value="ⲡⲁⲓ"/><!-- ⲡⲁⲓ -->
<feat xlink:href="#orig_1103" value="ⲡⲉ"/><!-- ⲡⲉ -->
<feat xlink:href="#orig_1104" value="ϩⲁ"/><!-- ϩⲁ -->
<feat xlink:href="#orig_1105" value="ⲧⲉ"/><!-- ⲧⲉ -->
<feat xlink:href="#orig_1106" value="ϩⲏ"/><!-- ϩⲏ -->
<feat xlink:href="#orig_1107" value="ⲙ"/><!-- ⲙ -->
<feat xlink:href="#orig_1108" value="ⲡ"/><!-- ⲡ -->
<feat xlink:href="#orig_1109" value="ⲥⲁⲃⲃⲁⲧⲟⲛ"/><!-- ⲥⲁⲃⲃⲁⲧⲟⲛ -->
<feat xlink:href="#orig_1110" value="ⲁ"/><!-- ⲁ -->
<feat xlink:href="#orig_1111" value="ϥ"/><!-- ϥ -->
<feat xlink:href="#orig_1112" value="ⲉⲓ"/><!-- ⲉⲓ -->
<feat xlink:href="#orig_1113" value="ⲛϭⲓ"/><!-- ⲛϭⲓ -->
<feat xlink:href="#orig_1114" value="ⲓⲱⲥⲏⲫ"/><!-- ⲓⲱⲥⲏⲫ -->
<feat xlink:href="#orig_1115" value="ⲡ"/><!-- ⲡ -->
<feat xlink:href="#orig_1116" value="ⲉⲃⲟⲗ"/><!-- ⲉⲃⲟⲗ -->
<feat xlink:href="#orig_1117" value="ϩⲛ"/><!-- ϩⲛ -->
<feat xlink:href="#orig_1118" value="ⲁⲣⲓⲙⲁⲑⲁⲓⲟⲥ"/><!-- ⲁⲣⲓⲙⲁⲑⲁⲓⲟⲥ -->
<feat xlink:href="#orig_1119" value="ⲉ"/><!-- ⲉ -->
<feat xlink:href="#orig_1120" value="ⲩ"/><!-- ⲩ -->
<feat xlink:href="#orig_1121" value="ⲣⲙⲙⲁⲟ"/><!-- ⲣⲙⲙⲁⲟ -->
<feat xlink:href="#orig_1122" value="ⲡⲉ"/><!-- ⲡⲉ -->
<feat xlink:href="#orig_1123" value="ⲃ"/><!-- ⲃ -->
<feat xlink:href="#orig_1124" value="ⲃⲟⲩⲗⲉⲩⲧⲏⲥ"/><!-- ⲃⲟⲩⲗⲉⲩⲧⲏⲥ -->
<feat xlink:href="#orig_1125" value="ⲛⲧⲟϥ"/><!-- ⲛⲧⲟϥ -->
<feat xlink:href="#orig_1126" value="ϩⲱⲱ"/><!-- ϩⲱⲱ -->
<feat xlink:href="#orig_1127" value="ϥ"/><!-- ϥ -->
<feat xlink:href="#orig_1128" value="ⲉ"/><!-- ⲉ -->
<feat xlink:href="#orig_1129" value="ϥ"/><!-- ϥ -->
<feat xlink:href="#orig_1130" value="ϭⲱϣⲧ"/><!-- ϭⲱϣⲧ -->
<feat xlink:href="#orig_1131" value="ⲉⲃⲟⲗ"/><!-- ⲉⲃⲟⲗ -->
<feat xlink:href="#orig_1132" value="ϩⲏⲧ"/><!-- ϩⲏⲧ -->
<feat xlink:href="#orig_1133" value="ⲥ"/><!-- ⲥ -->
<feat xlink:href="#orig_1134" value="ⲛ"/><!-- ⲛ -->
<feat xlink:href="#orig_1135" value="ⲧ"/><!-- ⲧ -->
<feat xlink:href="#orig_1136" value="ⲙⲛⲧⲣⲣⲟ"/><!-- ⲙⲛⲧ...ⲣⲣⲟ -->
<feat xlink:href="#orig_1138" value="ⲙ"/><!-- ⲙ -->
<feat xlink:href="#orig_1139" value="ⲡ"/><!-- ⲡ -->
<feat xlink:href="#orig_1140" value="ⲛⲟⲩⲧⲉ"/><!-- ⲛⲟⲩⲧⲉ -->
<feat xlink:href="#orig_1141" value="ⲁ"/><!-- ⲁ -->
<feat xlink:href="#orig_1142" value="ϥ"/><!-- ϥ -->
<feat xlink:href="#orig_1143" value="ⲧⲟⲗⲙⲁ"/><!-- ⲧⲟⲗⲙⲁ -->
<feat xlink:href="#orig_1144" value="ⲁ"/><!-- ⲁ -->
<feat xlink:href="#orig_1145" value="ϥ"/><!-- ϥ -->
<feat xlink:href="#orig_1146" value="ⲃⲱⲕ"/><!-- ⲃⲱⲕ -->
<feat xlink:href="#orig_1147" value="ⲉϩⲟⲩⲛ"/><!-- ⲉϩⲟⲩⲛ -->
<feat xlink:href="#orig_1148" value="ϣⲁ"/><!-- ϣⲁ -->
<feat xlink:href="#orig_1149" value="ⲡⲓⲗⲁⲧⲟⲥ"/><!-- ⲡⲓⲗⲁⲧⲟⲥ -->
<feat xlink:href="#orig_1150" value="ⲁ"/><!-- ⲁ -->
<feat xlink:href="#orig_1151" value="ϥ"/><!-- ϥ -->
<feat xlink:href="#orig_1152" value="ⲁⲓⲧⲓ"/><!-- ⲁⲓⲧⲓ -->
<feat xlink:href="#orig_1153" value="ⲙⲙⲟ"/><!-- ⲙⲙⲟ -->
<feat xlink:href="#orig_1154" value="ϥ"/><!-- ϥ -->
<feat xlink:href="#orig_1155" value="ⲙ"/><!-- ⲙ -->
<feat xlink:href="#orig_1156" value="ⲡ"/><!-- ⲡ -->
<feat xlink:href="#orig_1157" value="ⲥⲱⲙⲁ"/><!-- ⲥⲱⲙⲁ -->
<feat xlink:href="#orig_1158" value="ⲛ"/><!-- ⲛ -->
<feat xlink:href="#orig_1159" value="ⲓⲏⲥⲟⲩⲥ"/><!-- ⲓⲏⲥⲟⲩⲥ -->
<feat xlink:href="#orig_1160" value="ⲡⲓⲗⲁⲧⲟⲥ"/><!-- ⲡⲓⲗⲁⲧⲟⲥ -->
<feat xlink:href="#orig_1161" value="ⲇⲉ"/><!-- ⲇⲉ -->
<feat xlink:href="#orig_1162" value="ⲁ"/><!-- ⲁ -->
<feat xlink:href="#orig_1163" value="ϥ"/><!-- ϥ -->
<feat xlink:href="#orig_1164" value="ⲣϣⲡⲏⲣⲉ"/><!-- ⲣ...ϣⲡⲏⲣⲉ -->
<feat xlink:href="#orig_1166" value="ϫⲉ"/><!-- ϫⲉ -->
<feat xlink:href="#orig_1167" value="ⲉⲛⲉ"/><!-- ⲉⲛⲉ -->
<feat xlink:href="#orig_1168" value="ⲏⲇⲏ"/><!-- ⲏⲇⲏ -->
<feat xlink:href="#orig_1169" value="ⲁ"/><!-- ⲁ -->
<feat xlink:href="#orig_1170" value="ϥ"/><!-- ϥ -->
<feat xlink:href="#orig_1171" value="ⲙⲟⲩ"/><!-- ⲙⲟⲩ -->
<feat xlink:href="#orig_1172" value="ⲁⲩⲱ"/><!-- ⲁⲩⲱ -->
<feat xlink:href="#orig_1173" value="ⲛⲧⲉⲣⲉ"/><!-- ⲛⲧⲉⲣⲉ -->
<feat xlink:href="#orig_1174" value="ϥ"/><!-- ϥ -->
<feat xlink:href="#orig_1175" value="ⲙⲟⲩⲧⲉ"/><!-- ⲙⲟⲩⲧⲉ -->
<feat xlink:href="#orig_1176" value="ⲉ"/><!-- ⲉ -->
<feat xlink:href="#orig_1177" value="ⲡ"/><!-- ⲡ -->
<feat xlink:href="#orig_1178" value="ⲕⲉⲛⲧⲩⲣⲓⲱⲛ"/><!-- ⲕⲉⲛⲧⲩⲣⲓⲱⲛ -->
<feat xlink:href="#orig_1179" value="ⲁ"/><!-- ⲁ -->
<feat xlink:href="#orig_1180" value="ϥ"/><!-- ϥ -->
<feat xlink:href="#orig_1181" value="ϫⲛⲟⲩ"/><!-- ϫⲛⲟⲩ -->
<feat xlink:href="#orig_1182" value="ϥ"/><!-- ϥ -->
<feat xlink:href="#orig_1183" value="ϫⲉ"/><!-- ϫⲉ -->
<feat xlink:href="#orig_1184" value="ⲉⲛⲉ"/><!-- ⲉⲛⲉ -->
<feat xlink:href="#orig_1185" value="ⲁ"/><!-- ⲁ -->
<feat xlink:href="#orig_1186" value="ϥ"/><!-- ϥ -->
<feat xlink:href="#orig_1187" value="ⲱⲥⲕ"/><!-- ⲱⲥⲕ -->
<feat xlink:href="#orig_1188" value="ϫⲓⲛⲧ"/><!-- ϫⲓⲛⲧ -->
<feat xlink:href="#orig_1189" value="ⲁ"/><!-- ⲁ -->
<feat xlink:href="#orig_1190" value="ϥ"/><!-- ϥ -->
<feat xlink:href="#orig_1191" value="ⲙⲟⲩ"/><!-- ⲙⲟⲩ -->
<feat xlink:href="#orig_1192" value="."/><!-- . -->
<feat xlink:href="#orig_1193" value="ⲁⲩⲱ"/><!-- ⲁⲩⲱ -->
<feat xlink:href="#orig_1194" value="ⲛⲧⲉⲣⲉ"/><!-- ⲛⲧⲉⲣⲉ -->
<feat xlink:href="#orig_1195" value="ϥ"/><!-- ϥ -->
<feat xlink:href="#orig_1196" value="ⲉⲓⲙⲉ"/><!-- ⲉⲓⲙⲉ -->
<feat xlink:href="#orig_1197" value="ⲛⲧⲟⲟⲧ"/><!-- ⲛⲧⲟⲟⲧ -->
<feat xlink:href="#orig_1198" value="ϥ"/><!-- ϥ -->
<feat xlink:href="#orig_1199" value="ⲙ"/><!-- ⲙ -->
<feat xlink:href="#orig_1200" value="ⲡ"/><!-- ⲡ -->
<feat xlink:href="#orig_1201" value="ⲕⲉⲛⲧⲩⲣⲓⲱⲛ"/><!-- ⲕⲉⲛⲧⲩⲣⲓⲱⲛ -->
<feat xlink:href="#orig_1202" value="ⲁ"/><!-- ⲁ -->
<feat xlink:href="#orig_1203" value="ϥ"/><!-- ϥ -->
<feat xlink:href="#orig_1204" value="ⲭⲁⲣⲓⲍⲉ"/><!-- ⲭⲁⲣⲓⲍⲉ -->
<feat xlink:href="#orig_1205" value="ⲛ"/><!-- ⲛ -->
<feat xlink:href="#orig_1206" value="ⲓⲱⲥⲏⲫ"/><!-- ⲓⲱⲥⲏⲫ -->
<feat xlink:href="#orig_1207" value="ⲙ"/><!-- ⲙ -->
<feat xlink:href="#orig_1208" value="ⲡ"/><!-- ⲡ -->
<feat xlink:href="#orig_1209" value="ⲥⲱⲙⲁ"/><!-- ⲥⲱⲙⲁ -->
<feat xlink:href="#orig_1210" value="ⲛ"/><!-- ⲛ -->
<feat xlink:href="#orig_1211" value="ⲓⲏⲥⲟⲩⲥ"/><!-- ⲓⲏⲥⲟⲩⲥ -->
<feat xlink:href="#orig_1212" value="ⲁⲩⲱ"/><!-- ⲁⲩⲱ -->
<feat xlink:href="#orig_1213" value="ⲁ"/><!-- ⲁ -->
<feat xlink:href="#orig_1214" value="ϥ"/><!-- ϥ -->
<feat xlink:href="#orig_1215" value="ϣⲉⲡ"/><!-- ϣⲉⲡ -->
<feat xlink:href="#orig_1216" value="ⲟⲩ"/><!-- ⲟⲩ -->
<feat xlink:href="#orig_1217" value="ⲥⲓⲛⲇⲱⲛ"/><!-- ⲥⲓⲛⲇⲱⲛ -->
<feat xlink:href="#orig_1218" value="ⲁ"/><!-- ⲁ -->
<feat xlink:href="#orig_1219" value="ϥ"/><!-- ϥ -->
<feat xlink:href="#orig_1220" value="ⲙ"/><!-- ⲙ -->
<feat xlink:href="#orig_1221" value="ⲡ"/><!-- ⲡ -->
<feat xlink:href="#orig_1222" value="ⲥⲱⲙⲁ"/><!-- ⲥⲱⲙⲁ -->
<feat xlink:href="#orig_1223" value="ⲉⲡⲉⲥⲏⲧ"/><!-- ⲉⲡⲉⲥⲏⲧ -->
<feat xlink:href="#orig_1224" value="ⲡⲉ"/><!-- ⲡⲉ -->
<feat xlink:href="#orig_1225" value="ⲥⲏⲧ"/><!-- ⲥⲏⲧ -->
<feat xlink:href="#orig_1226" value="ⲁ"/><!-- ⲁ -->
<feat xlink:href="#orig_1227" value="ϥ"/><!-- ϥ -->
<feat xlink:href="#orig_1228" value="ϭⲗⲙⲗⲱⲙ"/><!-- ϭⲗⲙⲗⲱⲙ -->
<feat xlink:href="#orig_1229" value="ϥ"/><!-- ϥ -->
<feat xlink:href="#orig_1230" value="ϩⲛ"/><!-- ϩⲛ -->
<feat xlink:href="#orig_1231" value="ⲧ"/><!-- ⲧ -->
<feat xlink:href="#orig_1232" value="ⲥⲓⲛⲇⲱⲛ"/><!-- ⲥⲓⲛⲇⲱⲛ -->
<feat xlink:href="#orig_1233" value="."/><!-- . -->
<feat xlink:href="#orig_1234" value="ⲁ"/><!-- ⲁ -->
<feat xlink:href="#orig_1235" value="ϥ"/><!-- ϥ -->
<feat xlink:href="#orig_1236" value="ⲕⲁⲁ"/><!-- ⲕⲁⲁ -->
<feat xlink:href="#orig_1237" value="ϥ"/><!-- ϥ -->
<feat xlink:href="#orig_1238" value="ϩⲙ"/><!-- ϩⲙ -->
<feat xlink:href="#orig_1239" value="ⲡⲉϥ"/><!-- ⲡⲉϥ -->
<feat xlink:href="#orig_1240" value="ⲙϩⲁⲁⲩ"/><!-- ⲙϩⲁⲁⲩ -->
<feat xlink:href="#orig_1241" value="ⲉ"/><!-- ⲉ -->
<feat xlink:href="#orig_1242" value="ⲁ"/><!-- ⲁ -->
<feat xlink:href="#orig_1243" value="ⲩ"/><!-- ⲩ -->
<feat xlink:href="#orig_1244" value="ϣⲉⲧϣⲱⲧ"/><!-- ϣⲉⲧϣⲱⲧ -->
<feat xlink:href="#orig_1245" value="ϥ"/><!-- ϥ -->
<feat xlink:href="#orig_1246" value="ⲉⲃⲟⲗ"/><!-- ⲉⲃⲟⲗ -->
<feat xlink:href="#orig_1247" value="ϩⲛ"/><!-- ϩⲛ -->
<feat xlink:href="#orig_1248" value="ⲧ"/><!-- ⲧ -->
<feat xlink:href="#orig_1249" value="ⲡⲉⲧⲣⲁ"/><!-- ⲡⲉⲧⲣⲁ -->
<feat xlink:href="#orig_1250" value="ⲁⲩⲱ"/><!-- ⲁⲩⲱ -->
<feat xlink:href="#orig_1251" value="ⲁ"/><!-- ⲁ -->
<feat xlink:href="#orig_1252" value="ⲩ"/><!-- ⲩ -->
<feat xlink:href="#orig_1253" value="ⲥⲕⲣⲕⲣ"/><!-- ⲥⲕⲣⲕⲣ -->
<feat xlink:href="#orig_1254" value="ⲟⲩ"/><!-- ⲟⲩ -->
<feat xlink:href="#orig_1255" value="ⲱⲛⲉ"/><!-- ⲱⲛⲉ -->
<feat xlink:href="#orig_1256" value="ⲉ"/><!-- ⲉ -->
<feat xlink:href="#orig_1257" value="ⲣ"/><!-- ⲣ -->
<feat xlink:href="#orig_1258" value="ⲙ"/><!-- ⲙ -->
<feat xlink:href="#orig_1259" value="ⲡⲉ"/><!-- ⲡⲉ -->
<feat xlink:href="#orig_1260" value="ⲙϩⲁⲟⲩ"/><!-- ⲙϩⲁⲟⲩ -->
<feat xlink:href="#orig_1261" value="."/><!-- . -->
<feat xlink:href="#orig_1262" value="ⲙⲁⲣⲓⲁ"/><!-- ⲙⲁⲣⲓⲁ -->
<feat xlink:href="#orig_1263" value="ⲇⲉ"/><!-- ⲇⲉ -->
<feat xlink:href="#orig_1264" value="ⲧ"/><!-- ⲧ -->
<feat xlink:href="#orig_1265" value="ⲙⲁⲅⲇⲁⲗⲏⲛⲏ"/><!-- ⲙⲁⲅⲇⲁⲗⲏⲛⲏ -->
<feat xlink:href="#orig_1266" value="ⲁⲩⲱ"/><!-- ⲁⲩⲱ -->
<feat xlink:href="#orig_1267" value="ⲙⲁⲣⲓⲁ"/><!-- ⲙⲁⲣⲓⲁ -->
<feat xlink:href="#orig_1268" value="ⲧⲁ"/><!-- ⲧⲁ -->
<feat xlink:href="#orig_1269" value="ⲓⲱⲥⲏ"/><!-- ⲓⲱⲥⲏ -->
<feat xlink:href="#orig_1270" value="ⲛⲉ"/><!-- ⲛⲉ -->
<feat xlink:href="#orig_1271" value="ⲩ"/><!-- ⲩ -->
<feat xlink:href="#orig_1272" value="ⲛⲁⲩ"/><!-- ⲛⲁⲩ -->
<feat xlink:href="#orig_1273" value="ⲉ"/><!-- ⲉ -->
<feat xlink:href="#orig_1274" value="ⲡ"/><!-- ⲡ -->
<feat xlink:href="#orig_1275" value="ⲙⲁ"/><!-- ⲙⲁ -->
<feat xlink:href="#orig_1276" value="ⲛⲧ"/><!-- ⲛⲧ -->
<feat xlink:href="#orig_1277" value="ⲁ"/><!-- ⲁ -->
<feat xlink:href="#orig_1278" value="ⲩ"/><!-- ⲩ -->
<feat xlink:href="#orig_1279" value="ⲕⲁⲁ"/><!-- ⲕⲁⲁ -->
<feat xlink:href="#orig_1280" value="ϥ"/><!-- ϥ -->
<feat xlink:href="#orig_1281" value="ⲛϩⲏⲧ"/><!-- ⲛϩⲏⲧ -->
<feat xlink:href="#orig_1282" value="ϥ"/><!-- ϥ -->
<feat xlink:href="#orig_1283" value="."/><!-- . -->
</featList>
</paula>
