<?xml version='1.0' encoding='UTF-8'?><!DOCTYPE paula SYSTEM "paula_feat.dtd">
<paula version="1.1">
	<header paula_id="scriptorium.AP.131.n301.joshua.mark_func"/>
	<featList xmlns:xlink="http://www.w3.org/1999/xlink" type="func" xml:base="scriptorium.AP.131.n301.joshua.mark.xml">
		<feat xlink:href="#sSpan1" value="aux"/>
		<feat xlink:href="#sSpan12" value="det"/>
		<feat xlink:href="#sSpan14" value="nsubj"/>
		<feat xlink:href="#sSpan16" value="root"/>
		<feat xlink:href="#sSpan20" value="det"/>
		<feat xlink:href="#sSpan22" value="obj"/>
		<feat xlink:href="#sSpan24" value="mark"/>
		<feat xlink:href="#sSpan30" value="ccomp"/>
		<feat xlink:href="#sSpan32" value="csubj"/>
		<feat xlink:href="#sSpan34" value="obj"/>
		<feat xlink:href="#sSpan36" value="case"/>
		<feat xlink:href="#sSpan41" value="nmod"/>
		<feat xlink:href="#sSpan44" value="punct"/>
		<feat xlink:href="#sSpan49" value="punct"/>
		<feat xlink:href="#sSpan55" value="root"/>
		<feat xlink:href="#sSpan63" value="nsubj"/>
		<feat xlink:href="#sSpan65" value="case"/>
		<feat xlink:href="#sSpan69" value="det"/>
		<feat xlink:href="#sSpan71" value="dislocated"/>
		<feat xlink:href="#sSpan73" value="mark"/>
		<feat xlink:href="#sSpan79" value="nsubj"/>
		<feat xlink:href="#sSpan81" value="ccomp"/>
		<feat xlink:href="#sSpan83" value="case"/>
		<feat xlink:href="#sSpan88" value="obl"/>
		<feat xlink:href="#sSpan90" value="det"/>
		<feat xlink:href="#sSpan95" value="appos"/>
		<feat xlink:href="#sSpan97" value="case"/>
		<feat xlink:href="#sSpan102" value="nmod"/>
		<feat xlink:href="#sSpan104" value="mark"/>
		<feat xlink:href="#sSpan110" value="advmod"/>
		<feat xlink:href="#sSpan113" value="mark"/>
		<feat xlink:href="#sSpan117" value="nsubj"/>
		<feat xlink:href="#sSpan119" value="advcl"/>
		<feat xlink:href="#sSpan121" value="case"/>
		<feat xlink:href="#sSpan125" value="det"/>
		<feat xlink:href="#sSpan128" value="obl"/>
		<feat xlink:href="#sSpan130" value="punct"/>
		<feat xlink:href="#sSpan134" value="aux"/>
		<feat xlink:href="#sSpan139" value="det"/>
		<feat xlink:href="#sSpan141" value="nsubj"/>
		<feat xlink:href="#sSpan143" value="ccomp"/>
		<feat xlink:href="#sSpan148" value="case"/>
		<feat xlink:href="#sSpan152" value="obl"/>
		<feat xlink:href="#sSpan154" value="advmod"/>
		<feat xlink:href="#sSpan158" value="punct"/>
		<feat xlink:href="#sSpan162" value="punct"/></featList></paula>